{"12_head": {"device": ["2"], "batch_size": 1000, "kfold": 5, "usepytorch": true, "task_path": "./SentEval/data/", "cache_path": "./cache/", "result_path": "./ds_top_head_wise_results/", "optim": "rmsprop", "cbatch_size": 256, "tenacity": 3, "epoch_size": 2, "model_name": "bert-base-uncased", "task": "SICKEntailment", "num_head": 12, "intv_head": 1, "total_head": 40, "location": "head", "head_size": 64, "dropout": 0, "nhid": 0, "seed": 123, "classifier": {"nhid": 0, "optim": "rmsprop", "tenacity": 3, "epoch_size": 2, "dropout": 0, "batch_size": 256}, "heads": [[1, 9], [3, 2], [1, 8], [2, 2], [5, 3], [0, 4], [2, 7], [5, 8], [2, 4], [1, 0], [0, 3], [0, 0]], "devacc": 80.4, "acc": 78.93}, "3_head": {"device": ["2"], "batch_size": 1000, "kfold": 5, "usepytorch": true, "task_path": "./SentEval/data/", "cache_path": "./cache/", "result_path": "./ds_top_head_wise_results/", "optim": "rmsprop", "cbatch_size": 256, "tenacity": 3, "epoch_size": 2, "model_name": "bert-base-uncased", "task": "SICKEntailment", "num_head": 3, "intv_head": 1, "total_head": 40, "location": "head", "head_size": 64, "dropout": 0, "nhid": 0, "seed": 123, "classifier": {"nhid": 0, "optim": "rmsprop", "tenacity": 3, "epoch_size": 2, "dropout": 0, "batch_size": 256}, "heads": [[1, 9], [3, 2], [1, 8]], "devacc": 77.4, "acc": 76.84}, "6_head": {"device": ["2"], "batch_size": 1000, "kfold": 5, "usepytorch": true, "task_path": "./SentEval/data/", "cache_path": "./cache/", "result_path": "./ds_top_head_wise_results/", "optim": "rmsprop", "cbatch_size": 256, "tenacity": 3, "epoch_size": 2, "model_name": "bert-base-uncased", "task": "SICKEntailment", "num_head": 6, "intv_head": 1, "total_head": 40, "location": "head", "head_size": 64, "dropout": 0, "nhid": 0, "seed": 123, "classifier": {"nhid": 0, "optim": "rmsprop", "tenacity": 3, "epoch_size": 2, "dropout": 0, "batch_size": 256}, "heads": [[1, 9], [3, 2], [1, 8], [2, 2], [5, 3], [0, 4]], "devacc": 80.4, "acc": 78.49}, "9_head": {"device": ["2"], "batch_size": 1000, "kfold": 5, "usepytorch": true, "task_path": "./SentEval/data/", "cache_path": "./cache/", "result_path": "./ds_top_head_wise_results/", "optim": "rmsprop", "cbatch_size": 256, "tenacity": 3, "epoch_size": 2, "model_name": "bert-base-uncased", "task": "SICKEntailment", "num_head": 9, "intv_head": 1, "total_head": 40, "location": "head", "head_size": 64, "dropout": 0, "nhid": 0, "seed": 123, "classifier": {"nhid": 0, "optim": "rmsprop", "tenacity": 3, "epoch_size": 2, "dropout": 0, "batch_size": 256}, "heads": [[1, 9], [3, 2], [1, 8], [2, 2], [5, 3], [0, 4], [2, 7], [5, 8], [2, 4]], "devacc": 79.6, "acc": 78.57}, "15_head": {"device": ["2"], "batch_size": 1000, "kfold": 5, "usepytorch": true, "task_path": "./SentEval/data/", "cache_path": "./cache/", "result_path": "./ds_top_head_wise_results/", "optim": "rmsprop", "cbatch_size": 256, "tenacity": 3, "epoch_size": 2, "model_name": "bert-base-uncased", "task": "SICKEntailment", "num_head": 15, "intv_head": 1, "total_head": 40, "location": "head", "head_size": 64, "dropout": 0, "nhid": 0, "seed": 123, "classifier": {"nhid": 0, "optim": "rmsprop", "tenacity": 3, "epoch_size": 2, "dropout": 0, "batch_size": 256}, "heads": [[1, 9], [3, 2], [1, 8], [2, 2], [5, 3], [0, 4], [2, 7], [5, 8], [2, 4], [1, 0], [0, 3], [0, 0], [4, 2], [11, 5], [0, 9]], "devacc": 80.2, "acc": 79.7}, "18_head": {"device": ["2"], "batch_size": 1000, "kfold": 5, "usepytorch": true, "task_path": "./SentEval/data/", "cache_path": "./cache/", "result_path": "./ds_top_head_wise_results/", "optim": "rmsprop", "cbatch_size": 256, "tenacity": 3, "epoch_size": 2, "model_name": "bert-base-uncased", "task": "SICKEntailment", "num_head": 18, "intv_head": 1, "total_head": 40, "location": "head", "head_size": 64, "dropout": 0, "nhid": 0, "seed": 123, "classifier": {"nhid": 0, "optim": "rmsprop", "tenacity": 3, "epoch_size": 2, "dropout": 0, "batch_size": 256}, "heads": [[1, 9], [3, 2], [1, 8], [2, 2], [5, 3], [0, 4], [2, 7], [5, 8], [2, 4], [1, 0], [0, 3], [0, 0], [4, 2], [11, 5], [0, 9], [3, 4], [1, 10], [2, 8]], "devacc": 81.6, "acc": 79.56}, "21_head": {"device": ["2"], "batch_size": 1000, "kfold": 5, "usepytorch": true, "task_path": "./SentEval/data/", "cache_path": "./cache/", "result_path": "./ds_top_head_wise_results/", "optim": "rmsprop", "cbatch_size": 256, "tenacity": 3, "epoch_size": 2, "model_name": "bert-base-uncased", "task": "SICKEntailment", "num_head": 21, "intv_head": 1, "total_head": 40, "location": "head", "head_size": 64, "dropout": 0, "nhid": 0, "seed": 123, "classifier": {"nhid": 0, "optim": "rmsprop", "tenacity": 3, "epoch_size": 2, "dropout": 0, "batch_size": 256}, "heads": [[1, 9], [3, 2], [1, 8], [2, 2], [5, 3], [0, 4], [2, 7], [5, 8], [2, 4], [1, 0], [0, 3], [0, 0], [4, 2], [11, 5], [0, 9], [3, 4], [1, 10], [2, 8], [2, 10], [2, 6], [5, 4]], "devacc": 82.0, "acc": 80.21}, "24_head": {"device": ["2"], "batch_size": 1000, "kfold": 5, "usepytorch": true, "task_path": "./SentEval/data/", "cache_path": "./cache/", "result_path": "./ds_top_head_wise_results/", "optim": "rmsprop", "cbatch_size": 256, "tenacity": 3, "epoch_size": 2, "model_name": "bert-base-uncased", "task": "SICKEntailment", "num_head": 24, "intv_head": 1, "total_head": 40, "location": "head", "head_size": 64, "dropout": 0, "nhid": 0, "seed": 123, "classifier": {"nhid": 0, "optim": "rmsprop", "tenacity": 3, "epoch_size": 2, "dropout": 0, "batch_size": 256}, "heads": [[1, 9], [3, 2], [1, 8], [2, 2], [5, 3], [0, 4], [2, 7], [5, 8], [2, 4], [1, 0], [0, 3], [0, 0], [4, 2], [11, 5], [0, 9], [3, 4], [1, 10], [2, 8], [2, 10], [2, 6], [5, 4], [3, 8], [11, 11], [1, 5]], "devacc": 82.0, "acc": 79.97}, "27_head": {"device": ["2"], "batch_size": 1000, "kfold": 5, "usepytorch": true, "task_path": "./SentEval/data/", "cache_path": "./cache/", "result_path": "./ds_top_head_wise_results/", "optim": "rmsprop", "cbatch_size": 256, "tenacity": 3, "epoch_size": 2, "model_name": "bert-base-uncased", "task": "SICKEntailment", "num_head": 27, "intv_head": 1, "total_head": 40, "location": "head", "head_size": 64, "dropout": 0, "nhid": 0, "seed": 123, "classifier": {"nhid": 0, "optim": "rmsprop", "tenacity": 3, "epoch_size": 2, "dropout": 0, "batch_size": 256}, "heads": [[1, 9], [3, 2], [1, 8], [2, 2], [5, 3], [0, 4], [2, 7], [5, 8], [2, 4], [1, 0], [0, 3], [0, 0], [4, 2], [11, 5], [0, 9], [3, 4], [1, 10], [2, 8], [2, 10], [2, 6], [5, 4], [3, 8], [11, 11], [1, 5], [1, 11], [2, 1], [1, 3]], "devacc": 81.6, "acc": 79.64}, "30_head": {"device": ["2"], "batch_size": 1000, "kfold": 5, "usepytorch": true, "task_path": "./SentEval/data/", "cache_path": "./cache/", "result_path": "./ds_top_head_wise_results/", "optim": "rmsprop", "cbatch_size": 256, "tenacity": 3, "epoch_size": 2, "model_name": "bert-base-uncased", "task": "SICKEntailment", "num_head": 30, "intv_head": 1, "total_head": 40, "location": "head", "head_size": 64, "dropout": 0, "nhid": 0, "seed": 123, "classifier": {"nhid": 0, "optim": "rmsprop", "tenacity": 3, "epoch_size": 2, "dropout": 0, "batch_size": 256}, "heads": [[1, 9], [3, 2], [1, 8], [2, 2], [5, 3], [0, 4], [2, 7], [5, 8], [2, 4], [1, 0], [0, 3], [0, 0], [4, 2], [11, 5], [0, 9], [3, 4], [1, 10], [2, 8], [2, 10], [2, 6], [5, 4], [3, 8], [11, 11], [1, 5], [1, 11], [2, 1], [1, 3], [2, 3], [7, 1], [3, 7]], "devacc": 81.6, "acc": 79.62}, "33_head": {"device": ["2"], "batch_size": 1000, "kfold": 5, "usepytorch": true, "task_path": "./SentEval/data/", "cache_path": "./cache/", "result_path": "./ds_top_head_wise_results/", "optim": "rmsprop", "cbatch_size": 256, "tenacity": 3, "epoch_size": 2, "model_name": "bert-base-uncased", "task": "SICKEntailment", "num_head": 33, "intv_head": 1, "total_head": 40, "location": "head", "head_size": 64, "dropout": 0, "nhid": 0, "seed": 123, "classifier": {"nhid": 0, "optim": "rmsprop", "tenacity": 3, "epoch_size": 2, "dropout": 0, "batch_size": 256}, "heads": [[1, 9], [3, 2], [1, 8], [2, 2], [5, 3], [0, 4], [2, 7], [5, 8], [2, 4], [1, 0], [0, 3], [0, 0], [4, 2], [11, 5], [0, 9], [3, 4], [1, 10], [2, 8], [2, 10], [2, 6], [5, 4], [3, 8], [11, 11], [1, 5], [1, 11], [2, 1], [1, 3], [2, 3], [7, 1], [3, 7], [2, 5], [11, 9], [4, 9]], "devacc": 82.4, "acc": 79.89}, "36_head": {"device": ["2"], "batch_size": 1000, "kfold": 5, "usepytorch": true, "task_path": "./SentEval/data/", "cache_path": "./cache/", "result_path": "./ds_top_head_wise_results/", "optim": "rmsprop", "cbatch_size": 256, "tenacity": 3, "epoch_size": 2, "model_name": "bert-base-uncased", "task": "SICKEntailment", "num_head": 36, "intv_head": 1, "total_head": 40, "location": "head", "head_size": 64, "dropout": 0, "nhid": 0, "seed": 123, "classifier": {"nhid": 0, "optim": "rmsprop", "tenacity": 3, "epoch_size": 2, "dropout": 0, "batch_size": 256}, "heads": [[1, 9], [3, 2], [1, 8], [2, 2], [5, 3], [0, 4], [2, 7], [5, 8], [2, 4], [1, 0], [0, 3], [0, 0], [4, 2], [11, 5], [0, 9], [3, 4], [1, 10], [2, 8], [2, 10], [2, 6], [5, 4], [3, 8], [11, 11], [1, 5], [1, 11], [2, 1], [1, 3], [2, 3], [7, 1], [3, 7], [2, 5], [11, 9], [4, 9], [8, 7], [10, 3], [9, 10]], "devacc": 79.0, "acc": 79.36}, "39_head": {"device": ["2"], "batch_size": 1000, "kfold": 5, "usepytorch": true, "task_path": "./SentEval/data/", "cache_path": "./cache/", "result_path": "./ds_top_head_wise_results/", "optim": "rmsprop", "cbatch_size": 256, "tenacity": 3, "epoch_size": 2, "model_name": "bert-base-uncased", "task": "SICKEntailment", "num_head": 39, "intv_head": 1, "total_head": 40, "location": "head", "head_size": 64, "dropout": 0, "nhid": 0, "seed": 123, "classifier": {"nhid": 0, "optim": "rmsprop", "tenacity": 3, "epoch_size": 2, "dropout": 0, "batch_size": 256}, "heads": [[1, 9], [3, 2], [1, 8], [2, 2], [5, 3], [0, 4], [2, 7], [5, 8], [2, 4], [1, 0], [0, 3], [0, 0], [4, 2], [11, 5], [0, 9], [3, 4], [1, 10], [2, 8], [2, 10], [2, 6], [5, 4], [3, 8], [11, 11], [1, 5], [1, 11], [2, 1], [1, 3], [2, 3], [7, 1], [3, 7], [2, 5], [11, 9], [4, 9], [8, 7], [10, 3], [9, 10], [6, 5], [11, 8], [1, 4]], "devacc": 79.2, "acc": 79.66}, "42_head": {"device": ["2"], "batch_size": 1000, "kfold": 5, "usepytorch": true, "task_path": "./SentEval/data/", "cache_path": "./cache/", "result_path": "./ds_top_head_wise_results/", "optim": "rmsprop", "cbatch_size": 256, "tenacity": 3, "epoch_size": 2, "model_name": "bert-base-uncased", "task": "SICKEntailment", "num_head": 42, "intv_head": 3, "total_head": 144, "location": "head", "head_size": 64, "dropout": 0, "nhid": 0, "seed": 123, "classifier": {"nhid": 0, "optim": "rmsprop", "tenacity": 3, "epoch_size": 2, "dropout": 0, "batch_size": 256}, "heads": [[1, 9], [3, 2], [1, 8], [2, 2], [5, 3], [0, 4], [2, 7], [5, 8], [2, 4], [1, 0], [0, 3], [0, 0], [4, 2], [11, 5], [0, 9], [3, 4], [1, 10], [2, 8], [2, 10], [2, 6], [5, 4], [3, 8], [11, 11], [1, 5], [1, 11], [2, 1], [1, 3], [2, 3], [7, 1], [3, 7], [2, 5], [11, 9], [4, 9], [8, 7], [10, 3], [9, 10], [6, 5], [11, 8], [1, 4], [11, 6], [8, 0], [3, 6]], "devacc": 80.6, "acc": 79.48}, "45_head": {"device": ["2"], "batch_size": 1000, "kfold": 5, "usepytorch": true, "task_path": "./SentEval/data/", "cache_path": "./cache/", "result_path": "./ds_top_head_wise_results/", "optim": "rmsprop", "cbatch_size": 256, "tenacity": 3, "epoch_size": 2, "model_name": "bert-base-uncased", "task": "SICKEntailment", "num_head": 45, "intv_head": 3, "total_head": 144, "location": "head", "head_size": 64, "dropout": 0, "nhid": 0, "seed": 123, "classifier": {"nhid": 0, "optim": "rmsprop", "tenacity": 3, "epoch_size": 2, "dropout": 0, "batch_size": 256}, "heads": [[1, 9], [3, 2], [1, 8], [2, 2], [5, 3], [0, 4], [2, 7], [5, 8], [2, 4], [1, 0], [0, 3], [0, 0], [4, 2], [11, 5], [0, 9], [3, 4], [1, 10], [2, 8], [2, 10], [2, 6], [5, 4], [3, 8], [11, 11], [1, 5], [1, 11], [2, 1], [1, 3], [2, 3], [7, 1], [3, 7], [2, 5], [11, 9], [4, 9], [8, 7], [10, 3], [9, 10], [6, 5], [11, 8], [1, 4], [11, 6], [8, 0], [3, 6], [4, 4], [7, 5], [3, 11]], "devacc": 80.8, "acc": 79.99}, "48_head": {"device": ["2"], "batch_size": 1000, "kfold": 5, "usepytorch": true, "task_path": "./SentEval/data/", "cache_path": "./cache/", "result_path": "./ds_top_head_wise_results/", "optim": "rmsprop", "cbatch_size": 256, "tenacity": 3, "epoch_size": 2, "model_name": "bert-base-uncased", "task": "SICKEntailment", "num_head": 48, "intv_head": 3, "total_head": 144, "location": "head", "head_size": 64, "dropout": 0, "nhid": 0, "seed": 123, "classifier": {"nhid": 0, "optim": "rmsprop", "tenacity": 3, "epoch_size": 2, "dropout": 0, "batch_size": 256}, "heads": [[1, 9], [3, 2], [1, 8], [2, 2], [5, 3], [0, 4], [2, 7], [5, 8], [2, 4], [1, 0], [0, 3], [0, 0], [4, 2], [11, 5], [0, 9], [3, 4], [1, 10], [2, 8], [2, 10], [2, 6], [5, 4], [3, 8], [11, 11], [1, 5], [1, 11], [2, 1], [1, 3], [2, 3], [7, 1], [3, 7], [2, 5], [11, 9], [4, 9], [8, 7], [10, 3], [9, 10], [6, 5], [11, 8], [1, 4], [11, 6], [8, 0], [3, 6], [4, 4], [7, 5], [3, 11], [9, 8], [1, 2], [8, 8]], "devacc": 80.6, "acc": 80.15}, "51_head": {"device": ["2"], "batch_size": 1000, "kfold": 5, "usepytorch": true, "task_path": "./SentEval/data/", "cache_path": "./cache/", "result_path": "./ds_top_head_wise_results/", "optim": "rmsprop", "cbatch_size": 256, "tenacity": 3, "epoch_size": 2, "model_name": "bert-base-uncased", "task": "SICKEntailment", "num_head": 51, "intv_head": 3, "total_head": 144, "location": "head", "head_size": 64, "dropout": 0, "nhid": 0, "seed": 123, "classifier": {"nhid": 0, "optim": "rmsprop", "tenacity": 3, "epoch_size": 2, "dropout": 0, "batch_size": 256}, "heads": [[1, 9], [3, 2], [1, 8], [2, 2], [5, 3], [0, 4], [2, 7], [5, 8], [2, 4], [1, 0], [0, 3], [0, 0], [4, 2], [11, 5], [0, 9], [3, 4], [1, 10], [2, 8], [2, 10], [2, 6], [5, 4], [3, 8], [11, 11], [1, 5], [1, 11], [2, 1], [1, 3], [2, 3], [7, 1], [3, 7], [2, 5], [11, 9], [4, 9], [8, 7], [10, 3], [9, 10], [6, 5], [11, 8], [1, 4], [11, 6], [8, 0], [3, 6], [4, 4], [7, 5], [3, 11], [9, 8], [1, 2], [8, 8], [6, 1], [10, 7], [0, 5]], "devacc": 80.2, "acc": 80.21}, "54_head": {"device": ["2"], "batch_size": 1000, "kfold": 5, "usepytorch": true, "task_path": "./SentEval/data/", "cache_path": "./cache/", "result_path": "./ds_top_head_wise_results/", "optim": "rmsprop", "cbatch_size": 256, "tenacity": 3, "epoch_size": 2, "model_name": "bert-base-uncased", "task": "SICKEntailment", "num_head": 54, "intv_head": 3, "total_head": 144, "location": "head", "head_size": 64, "dropout": 0, "nhid": 0, "seed": 123, "classifier": {"nhid": 0, "optim": "rmsprop", "tenacity": 3, "epoch_size": 2, "dropout": 0, "batch_size": 256}, "heads": [[1, 9], [3, 2], [1, 8], [2, 2], [5, 3], [0, 4], [2, 7], [5, 8], [2, 4], [1, 0], [0, 3], [0, 0], [4, 2], [11, 5], [0, 9], [3, 4], [1, 10], [2, 8], [2, 10], [2, 6], [5, 4], [3, 8], [11, 11], [1, 5], [1, 11], [2, 1], [1, 3], [2, 3], [7, 1], [3, 7], [2, 5], [11, 9], [4, 9], [8, 7], [10, 3], [9, 10], [6, 5], [11, 8], [1, 4], [11, 6], [8, 0], [3, 6], [4, 4], [7, 5], [3, 11], [9, 8], [1, 2], [8, 8], [6, 1], [10, 7], [0, 5], [11, 2], [8, 1], [1, 1]], "devacc": 79.0, "acc": 79.46}, "57_head": {"device": ["2"], "batch_size": 1000, "kfold": 5, "usepytorch": true, "task_path": "./SentEval/data/", "cache_path": "./cache/", "result_path": "./ds_top_head_wise_results/", "optim": "rmsprop", "cbatch_size": 256, "tenacity": 3, "epoch_size": 2, "model_name": "bert-base-uncased", "task": "SICKEntailment", "num_head": 57, "intv_head": 3, "total_head": 144, "location": "head", "head_size": 64, "dropout": 0, "nhid": 0, "seed": 123, "classifier": {"nhid": 0, "optim": "rmsprop", "tenacity": 3, "epoch_size": 2, "dropout": 0, "batch_size": 256}, "heads": [[1, 9], [3, 2], [1, 8], [2, 2], [5, 3], [0, 4], [2, 7], [5, 8], [2, 4], [1, 0], [0, 3], [0, 0], [4, 2], [11, 5], [0, 9], [3, 4], [1, 10], [2, 8], [2, 10], [2, 6], [5, 4], [3, 8], [11, 11], [1, 5], [1, 11], [2, 1], [1, 3], [2, 3], [7, 1], [3, 7], [2, 5], [11, 9], [4, 9], [8, 7], [10, 3], [9, 10], [6, 5], [11, 8], [1, 4], [11, 6], [8, 0], [3, 6], [4, 4], [7, 5], [3, 11], [9, 8], [1, 2], [8, 8], [6, 1], [10, 7], [0, 5], [11, 2], [8, 1], [1, 1], [0, 10], [9, 0], [2, 11]], "devacc": 79.6, "acc": 77.51}, "60_head": {"device": ["2"], "batch_size": 1000, "kfold": 5, "usepytorch": true, "task_path": "./SentEval/data/", "cache_path": "./cache/", "result_path": "./ds_top_head_wise_results/", "optim": "rmsprop", "cbatch_size": 256, "tenacity": 3, "epoch_size": 2, "model_name": "bert-base-uncased", "task": "SICKEntailment", "num_head": 60, "intv_head": 3, "total_head": 144, "location": "head", "head_size": 64, "dropout": 0, "nhid": 0, "seed": 123, "classifier": {"nhid": 0, "optim": "rmsprop", "tenacity": 3, "epoch_size": 2, "dropout": 0, "batch_size": 256}, "heads": [[1, 9], [3, 2], [1, 8], [2, 2], [5, 3], [0, 4], [2, 7], [5, 8], [2, 4], [1, 0], [0, 3], [0, 0], [4, 2], [11, 5], [0, 9], [3, 4], [1, 10], [2, 8], [2, 10], [2, 6], [5, 4], [3, 8], [11, 11], [1, 5], [1, 11], [2, 1], [1, 3], [2, 3], [7, 1], [3, 7], [2, 5], [11, 9], [4, 9], [8, 7], [10, 3], [9, 10], [6, 5], [11, 8], [1, 4], [11, 6], [8, 0], [3, 6], [4, 4], [7, 5], [3, 11], [9, 8], [1, 2], [8, 8], [6, 1], [10, 7], [0, 5], [11, 2], [8, 1], [1, 1], [0, 10], [9, 0], [2, 11], [11, 1], [3, 3], [6, 4]], "devacc": 80.8, "acc": 80.07}, "63_head": {"device": ["2"], "batch_size": 1000, "kfold": 5, "usepytorch": true, "task_path": "./SentEval/data/", "cache_path": "./cache/", "result_path": "./ds_top_head_wise_results/", "optim": "rmsprop", "cbatch_size": 256, "tenacity": 3, "epoch_size": 2, "model_name": "bert-base-uncased", "task": "SICKEntailment", "num_head": 63, "intv_head": 3, "total_head": 144, "location": "head", "head_size": 64, "dropout": 0, "nhid": 0, "seed": 123, "classifier": {"nhid": 0, "optim": "rmsprop", "tenacity": 3, "epoch_size": 2, "dropout": 0, "batch_size": 256}, "heads": [[1, 9], [3, 2], [1, 8], [2, 2], [5, 3], [0, 4], [2, 7], [5, 8], [2, 4], [1, 0], [0, 3], [0, 0], [4, 2], [11, 5], [0, 9], [3, 4], [1, 10], [2, 8], [2, 10], [2, 6], [5, 4], [3, 8], [11, 11], [1, 5], [1, 11], [2, 1], [1, 3], [2, 3], [7, 1], [3, 7], [2, 5], [11, 9], [4, 9], [8, 7], [10, 3], [9, 10], [6, 5], [11, 8], [1, 4], [11, 6], [8, 0], [3, 6], [4, 4], [7, 5], [3, 11], [9, 8], [1, 2], [8, 8], [6, 1], [10, 7], [0, 5], [11, 2], [8, 1], [1, 1], [0, 10], [9, 0], [2, 11], [11, 1], [3, 3], [6, 4], [1, 7], [5, 7], [6, 8]], "devacc": 81.6, "acc": 79.03}, "66_head": {"device": ["2"], "batch_size": 1000, "kfold": 5, "usepytorch": true, "task_path": "./SentEval/data/", "cache_path": "./cache/", "result_path": "./ds_top_head_wise_results/", "optim": "rmsprop", "cbatch_size": 256, "tenacity": 3, "epoch_size": 2, "model_name": "bert-base-uncased", "task": "SICKEntailment", "num_head": 66, "intv_head": 3, "total_head": 144, "location": "head", "head_size": 64, "dropout": 0, "nhid": 0, "seed": 123, "classifier": {"nhid": 0, "optim": "rmsprop", "tenacity": 3, "epoch_size": 2, "dropout": 0, "batch_size": 256}, "heads": [[1, 9], [3, 2], [1, 8], [2, 2], [5, 3], [0, 4], [2, 7], [5, 8], [2, 4], [1, 0], [0, 3], [0, 0], [4, 2], [11, 5], [0, 9], [3, 4], [1, 10], [2, 8], [2, 10], [2, 6], [5, 4], [3, 8], [11, 11], [1, 5], [1, 11], [2, 1], [1, 3], [2, 3], [7, 1], [3, 7], [2, 5], [11, 9], [4, 9], [8, 7], [10, 3], [9, 10], [6, 5], [11, 8], [1, 4], [11, 6], [8, 0], [3, 6], [4, 4], [7, 5], [3, 11], [9, 8], [1, 2], [8, 8], [6, 1], [10, 7], [0, 5], [11, 2], [8, 1], [1, 1], [0, 10], [9, 0], [2, 11], [11, 1], [3, 3], [6, 4], [1, 7], [5, 7], [6, 8], [4, 8], [11, 3], [11, 4]], "devacc": 79.2, "acc": 79.6}, "69_head": {"device": ["2"], "batch_size": 1000, "kfold": 5, "usepytorch": true, "task_path": "./SentEval/data/", "cache_path": "./cache/", "result_path": "./ds_top_head_wise_results/", "optim": "rmsprop", "cbatch_size": 256, "tenacity": 3, "epoch_size": 2, "model_name": "bert-base-uncased", "task": "SICKEntailment", "num_head": 69, "intv_head": 3, "total_head": 144, "location": "head", "head_size": 64, "dropout": 0, "nhid": 0, "seed": 123, "classifier": {"nhid": 0, "optim": "rmsprop", "tenacity": 3, "epoch_size": 2, "dropout": 0, "batch_size": 256}, "heads": [[1, 9], [3, 2], [1, 8], [2, 2], [5, 3], [0, 4], [2, 7], [5, 8], [2, 4], [1, 0], [0, 3], [0, 0], [4, 2], [11, 5], [0, 9], [3, 4], [1, 10], [2, 8], [2, 10], [2, 6], [5, 4], [3, 8], [11, 11], [1, 5], [1, 11], [2, 1], [1, 3], [2, 3], [7, 1], [3, 7], [2, 5], [11, 9], [4, 9], [8, 7], [10, 3], [9, 10], [6, 5], [11, 8], [1, 4], [11, 6], [8, 0], [3, 6], [4, 4], [7, 5], [3, 11], [9, 8], [1, 2], [8, 8], [6, 1], [10, 7], [0, 5], [11, 2], [8, 1], [1, 1], [0, 10], [9, 0], [2, 11], [11, 1], [3, 3], [6, 4], [1, 7], [5, 7], [6, 8], [4, 8], [11, 3], [11, 4], [4, 1], [10, 6], [7, 6]], "devacc": 79.6, "acc": 78.59}, "72_head": {"device": ["2"], "batch_size": 1000, "kfold": 5, "usepytorch": true, "task_path": "./SentEval/data/", "cache_path": "./cache/", "result_path": "./ds_top_head_wise_results/", "optim": "rmsprop", "cbatch_size": 256, "tenacity": 3, "epoch_size": 2, "model_name": "bert-base-uncased", "task": "SICKEntailment", "num_head": 72, "intv_head": 3, "total_head": 144, "location": "head", "head_size": 64, "dropout": 0, "nhid": 0, "seed": 123, "classifier": {"nhid": 0, "optim": "rmsprop", "tenacity": 3, "epoch_size": 2, "dropout": 0, "batch_size": 256}, "heads": [[1, 9], [3, 2], [1, 8], [2, 2], [5, 3], [0, 4], [2, 7], [5, 8], [2, 4], [1, 0], [0, 3], [0, 0], [4, 2], [11, 5], [0, 9], [3, 4], [1, 10], [2, 8], [2, 10], [2, 6], [5, 4], [3, 8], [11, 11], [1, 5], [1, 11], [2, 1], [1, 3], [2, 3], [7, 1], [3, 7], [2, 5], [11, 9], [4, 9], [8, 7], [10, 3], [9, 10], [6, 5], [11, 8], [1, 4], [11, 6], [8, 0], [3, 6], [4, 4], [7, 5], [3, 11], [9, 8], [1, 2], [8, 8], [6, 1], [10, 7], [0, 5], [11, 2], [8, 1], [1, 1], [0, 10], [9, 0], [2, 11], [11, 1], [3, 3], [6, 4], [1, 7], [5, 7], [6, 8], [4, 8], [11, 3], [11, 4], [4, 1], [10, 6], [7, 6], [10, 11], [4, 10], [3, 1]], "devacc": 79.4, "acc": 77.63}, "75_head": {"device": ["2"], "batch_size": 1000, "kfold": 5, "usepytorch": true, "task_path": "./SentEval/data/", "cache_path": "./cache/", "result_path": "./ds_top_head_wise_results/", "optim": "rmsprop", "cbatch_size": 256, "tenacity": 3, "epoch_size": 2, "model_name": "bert-base-uncased", "task": "SICKEntailment", "num_head": 75, "intv_head": 3, "total_head": 144, "location": "head", "head_size": 64, "dropout": 0, "nhid": 0, "seed": 123, "classifier": {"nhid": 0, "optim": "rmsprop", "tenacity": 3, "epoch_size": 2, "dropout": 0, "batch_size": 256}, "heads": [[1, 9], [3, 2], [1, 8], [2, 2], [5, 3], [0, 4], [2, 7], [5, 8], [2, 4], [1, 0], [0, 3], [0, 0], [4, 2], [11, 5], [0, 9], [3, 4], [1, 10], [2, 8], [2, 10], [2, 6], [5, 4], [3, 8], [11, 11], [1, 5], [1, 11], [2, 1], [1, 3], [2, 3], [7, 1], [3, 7], [2, 5], [11, 9], [4, 9], [8, 7], [10, 3], [9, 10], [6, 5], [11, 8], [1, 4], [11, 6], [8, 0], [3, 6], [4, 4], [7, 5], [3, 11], [9, 8], [1, 2], [8, 8], [6, 1], [10, 7], [0, 5], [11, 2], [8, 1], [1, 1], [0, 10], [9, 0], [2, 11], [11, 1], [3, 3], [6, 4], [1, 7], [5, 7], [6, 8], [4, 8], [11, 3], [11, 4], [4, 1], [10, 6], [7, 6], [10, 11], [4, 10], [3, 1], [10, 0], [11, 0], [0, 2]], "devacc": 79.0, "acc": 76.86}, "78_head": {"device": ["2"], "batch_size": 1000, "kfold": 5, "usepytorch": true, "task_path": "./SentEval/data/", "cache_path": "./cache/", "result_path": "./ds_top_head_wise_results/", "optim": "rmsprop", "cbatch_size": 256, "tenacity": 3, "epoch_size": 2, "model_name": "bert-base-uncased", "task": "SICKEntailment", "num_head": 78, "intv_head": 3, "total_head": 144, "location": "head", "head_size": 64, "dropout": 0, "nhid": 0, "seed": 123, "classifier": {"nhid": 0, "optim": "rmsprop", "tenacity": 3, "epoch_size": 2, "dropout": 0, "batch_size": 256}, "heads": [[1, 9], [3, 2], [1, 8], [2, 2], [5, 3], [0, 4], [2, 7], [5, 8], [2, 4], [1, 0], [0, 3], [0, 0], [4, 2], [11, 5], [0, 9], [3, 4], [1, 10], [2, 8], [2, 10], [2, 6], [5, 4], [3, 8], [11, 11], [1, 5], [1, 11], [2, 1], [1, 3], [2, 3], [7, 1], [3, 7], [2, 5], [11, 9], [4, 9], [8, 7], [10, 3], [9, 10], [6, 5], [11, 8], [1, 4], [11, 6], [8, 0], [3, 6], [4, 4], [7, 5], [3, 11], [9, 8], [1, 2], [8, 8], [6, 1], [10, 7], [0, 5], [11, 2], [8, 1], [1, 1], [0, 10], [9, 0], [2, 11], [11, 1], [3, 3], [6, 4], [1, 7], [5, 7], [6, 8], [4, 8], [11, 3], [11, 4], [4, 1], [10, 6], [7, 6], [10, 11], [4, 10], [3, 1], [10, 0], [11, 0], [0, 2], [3, 5], [10, 10], [1, 6]], "devacc": 78.2, "acc": 76.52}, "81_head": {"device": ["2"], "batch_size": 1000, "kfold": 5, "usepytorch": true, "task_path": "./SentEval/data/", "cache_path": "./cache/", "result_path": "./ds_top_head_wise_results/", "optim": "rmsprop", "cbatch_size": 256, "tenacity": 3, "epoch_size": 2, "model_name": "bert-base-uncased", "task": "SICKEntailment", "num_head": 81, "intv_head": 3, "total_head": 144, "location": "head", "head_size": 64, "dropout": 0, "nhid": 0, "seed": 123, "classifier": {"nhid": 0, "optim": "rmsprop", "tenacity": 3, "epoch_size": 2, "dropout": 0, "batch_size": 256}, "heads": [[1, 9], [3, 2], [1, 8], [2, 2], [5, 3], [0, 4], [2, 7], [5, 8], [2, 4], [1, 0], [0, 3], [0, 0], [4, 2], [11, 5], [0, 9], [3, 4], [1, 10], [2, 8], [2, 10], [2, 6], [5, 4], [3, 8], [11, 11], [1, 5], [1, 11], [2, 1], [1, 3], [2, 3], [7, 1], [3, 7], [2, 5], [11, 9], [4, 9], [8, 7], [10, 3], [9, 10], [6, 5], [11, 8], [1, 4], [11, 6], [8, 0], [3, 6], [4, 4], [7, 5], [3, 11], [9, 8], [1, 2], [8, 8], [6, 1], [10, 7], [0, 5], [11, 2], [8, 1], [1, 1], [0, 10], [9, 0], [2, 11], [11, 1], [3, 3], [6, 4], [1, 7], [5, 7], [6, 8], [4, 8], [11, 3], [11, 4], [4, 1], [10, 6], [7, 6], [10, 11], [4, 10], [3, 1], [10, 0], [11, 0], [0, 2], [3, 5], [10, 10], [1, 6], [3, 9], [8, 4], [6, 10]], "devacc": 79.8, "acc": 79.78}, "84_head": {"device": ["2"], "batch_size": 1000, "kfold": 5, "usepytorch": true, "task_path": "./SentEval/data/", "cache_path": "./cache/", "result_path": "./ds_top_head_wise_results/", "optim": "rmsprop", "cbatch_size": 256, "tenacity": 3, "epoch_size": 2, "model_name": "bert-base-uncased", "task": "SICKEntailment", "num_head": 84, "intv_head": 3, "total_head": 144, "location": "head", "head_size": 64, "dropout": 0, "nhid": 0, "seed": 123, "classifier": {"nhid": 0, "optim": "rmsprop", "tenacity": 3, "epoch_size": 2, "dropout": 0, "batch_size": 256}, "heads": [[1, 9], [3, 2], [1, 8], [2, 2], [5, 3], [0, 4], [2, 7], [5, 8], [2, 4], [1, 0], [0, 3], [0, 0], [4, 2], [11, 5], [0, 9], [3, 4], [1, 10], [2, 8], [2, 10], [2, 6], [5, 4], [3, 8], [11, 11], [1, 5], [1, 11], [2, 1], [1, 3], [2, 3], [7, 1], [3, 7], [2, 5], [11, 9], [4, 9], [8, 7], [10, 3], [9, 10], [6, 5], [11, 8], [1, 4], [11, 6], [8, 0], [3, 6], [4, 4], [7, 5], [3, 11], [9, 8], [1, 2], [8, 8], [6, 1], [10, 7], [0, 5], [11, 2], [8, 1], [1, 1], [0, 10], [9, 0], [2, 11], [11, 1], [3, 3], [6, 4], [1, 7], [5, 7], [6, 8], [4, 8], [11, 3], [11, 4], [4, 1], [10, 6], [7, 6], [10, 11], [4, 10], [3, 1], [10, 0], [11, 0], [0, 2], [3, 5], [10, 10], [1, 6], [3, 9], [8, 4], [6, 10], [7, 8], [6, 2], [4, 0]], "devacc": 80.0, "acc": 80.11}, "87_head": {"device": ["2"], "batch_size": 1000, "kfold": 5, "usepytorch": true, "task_path": "./SentEval/data/", "cache_path": "./cache/", "result_path": "./ds_top_head_wise_results/", "optim": "rmsprop", "cbatch_size": 256, "tenacity": 3, "epoch_size": 2, "model_name": "bert-base-uncased", "task": "SICKEntailment", "num_head": 87, "intv_head": 3, "total_head": 144, "location": "head", "head_size": 64, "dropout": 0, "nhid": 0, "seed": 123, "classifier": {"nhid": 0, "optim": "rmsprop", "tenacity": 3, "epoch_size": 2, "dropout": 0, "batch_size": 256}, "heads": [[1, 9], [3, 2], [1, 8], [2, 2], [5, 3], [0, 4], [2, 7], [5, 8], [2, 4], [1, 0], [0, 3], [0, 0], [4, 2], [11, 5], [0, 9], [3, 4], [1, 10], [2, 8], [2, 10], [2, 6], [5, 4], [3, 8], [11, 11], [1, 5], [1, 11], [2, 1], [1, 3], [2, 3], [7, 1], [3, 7], [2, 5], [11, 9], [4, 9], [8, 7], [10, 3], [9, 10], [6, 5], [11, 8], [1, 4], [11, 6], [8, 0], [3, 6], [4, 4], [7, 5], [3, 11], [9, 8], [1, 2], [8, 8], [6, 1], [10, 7], [0, 5], [11, 2], [8, 1], [1, 1], [0, 10], [9, 0], [2, 11], [11, 1], [3, 3], [6, 4], [1, 7], [5, 7], [6, 8], [4, 8], [11, 3], [11, 4], [4, 1], [10, 6], [7, 6], [10, 11], [4, 10], [3, 1], [10, 0], [11, 0], [0, 2], [3, 5], [10, 10], [1, 6], [3, 9], [8, 4], [6, 10], [7, 8], [6, 2], [4, 0], [9, 11], [10, 4], [6, 0]], "devacc": 80.6, "acc": 79.5}, "90_head": {"device": ["2"], "batch_size": 1000, "kfold": 5, "usepytorch": true, "task_path": "./SentEval/data/", "cache_path": "./cache/", "result_path": "./ds_top_head_wise_results/", "optim": "rmsprop", "cbatch_size": 256, "tenacity": 3, "epoch_size": 2, "model_name": "bert-base-uncased", "task": "SICKEntailment", "num_head": 90, "intv_head": 3, "total_head": 144, "location": "head", "head_size": 64, "dropout": 0, "nhid": 0, "seed": 123, "classifier": {"nhid": 0, "optim": "rmsprop", "tenacity": 3, "epoch_size": 2, "dropout": 0, "batch_size": 256}, "heads": [[1, 9], [3, 2], [1, 8], [2, 2], [5, 3], [0, 4], [2, 7], [5, 8], [2, 4], [1, 0], [0, 3], [0, 0], [4, 2], [11, 5], [0, 9], [3, 4], [1, 10], [2, 8], [2, 10], [2, 6], [5, 4], [3, 8], [11, 11], [1, 5], [1, 11], [2, 1], [1, 3], [2, 3], [7, 1], [3, 7], [2, 5], [11, 9], [4, 9], [8, 7], [10, 3], [9, 10], [6, 5], [11, 8], [1, 4], [11, 6], [8, 0], [3, 6], [4, 4], [7, 5], [3, 11], [9, 8], [1, 2], [8, 8], [6, 1], [10, 7], [0, 5], [11, 2], [8, 1], [1, 1], [0, 10], [9, 0], [2, 11], [11, 1], [3, 3], [6, 4], [1, 7], [5, 7], [6, 8], [4, 8], [11, 3], [11, 4], [4, 1], [10, 6], [7, 6], [10, 11], [4, 10], [3, 1], [10, 0], [11, 0], [0, 2], [3, 5], [10, 10], [1, 6], [3, 9], [8, 4], [6, 10], [7, 8], [6, 2], [4, 0], [9, 11], [10, 4], [6, 0], [3, 10], [7, 10], [2, 0]], "devacc": 79.2, "acc": 79.3}, "93_head": {"device": ["2"], "batch_size": 1000, "kfold": 5, "usepytorch": true, "task_path": "./SentEval/data/", "cache_path": "./cache/", "result_path": "./ds_top_head_wise_results/", "optim": "rmsprop", "cbatch_size": 256, "tenacity": 3, "epoch_size": 2, "model_name": "bert-base-uncased", "task": "SICKEntailment", "num_head": 93, "intv_head": 3, "total_head": 144, "location": "head", "head_size": 64, "dropout": 0, "nhid": 0, "seed": 123, "classifier": {"nhid": 0, "optim": "rmsprop", "tenacity": 3, "epoch_size": 2, "dropout": 0, "batch_size": 256}, "heads": [[1, 9], [3, 2], [1, 8], [2, 2], [5, 3], [0, 4], [2, 7], [5, 8], [2, 4], [1, 0], [0, 3], [0, 0], [4, 2], [11, 5], [0, 9], [3, 4], [1, 10], [2, 8], [2, 10], [2, 6], [5, 4], [3, 8], [11, 11], [1, 5], [1, 11], [2, 1], [1, 3], [2, 3], [7, 1], [3, 7], [2, 5], [11, 9], [4, 9], [8, 7], [10, 3], [9, 10], [6, 5], [11, 8], [1, 4], [11, 6], [8, 0], [3, 6], [4, 4], [7, 5], [3, 11], [9, 8], [1, 2], [8, 8], [6, 1], [10, 7], [0, 5], [11, 2], [8, 1], [1, 1], [0, 10], [9, 0], [2, 11], [11, 1], [3, 3], [6, 4], [1, 7], [5, 7], [6, 8], [4, 8], [11, 3], [11, 4], [4, 1], [10, 6], [7, 6], [10, 11], [4, 10], [3, 1], [10, 0], [11, 0], [0, 2], [3, 5], [10, 10], [1, 6], [3, 9], [8, 4], [6, 10], [7, 8], [6, 2], [4, 0], [9, 11], [10, 4], [6, 0], [3, 10], [7, 10], [2, 0], [10, 1], [11, 7], [10, 2]], "devacc": 80.2, "acc": 78.02}, "96_head": {"device": ["2"], "batch_size": 1000, "kfold": 5, "usepytorch": true, "task_path": "./SentEval/data/", "cache_path": "./cache/", "result_path": "./ds_top_head_wise_results/", "optim": "rmsprop", "cbatch_size": 256, "tenacity": 3, "epoch_size": 2, "model_name": "bert-base-uncased", "task": "SICKEntailment", "num_head": 96, "intv_head": 3, "total_head": 144, "location": "head", "head_size": 64, "dropout": 0, "nhid": 0, "seed": 123, "classifier": {"nhid": 0, "optim": "rmsprop", "tenacity": 3, "epoch_size": 2, "dropout": 0, "batch_size": 256}, "heads": [[1, 9], [3, 2], [1, 8], [2, 2], [5, 3], [0, 4], [2, 7], [5, 8], [2, 4], [1, 0], [0, 3], [0, 0], [4, 2], [11, 5], [0, 9], [3, 4], [1, 10], [2, 8], [2, 10], [2, 6], [5, 4], [3, 8], [11, 11], [1, 5], [1, 11], [2, 1], [1, 3], [2, 3], [7, 1], [3, 7], [2, 5], [11, 9], [4, 9], [8, 7], [10, 3], [9, 10], [6, 5], [11, 8], [1, 4], [11, 6], [8, 0], [3, 6], [4, 4], [7, 5], [3, 11], [9, 8], [1, 2], [8, 8], [6, 1], [10, 7], [0, 5], [11, 2], [8, 1], [1, 1], [0, 10], [9, 0], [2, 11], [11, 1], [3, 3], [6, 4], [1, 7], [5, 7], [6, 8], [4, 8], [11, 3], [11, 4], [4, 1], [10, 6], [7, 6], [10, 11], [4, 10], [3, 1], [10, 0], [11, 0], [0, 2], [3, 5], [10, 10], [1, 6], [3, 9], [8, 4], [6, 10], [7, 8], [6, 2], [4, 0], [9, 11], [10, 4], [6, 0], [3, 10], [7, 10], [2, 0], [10, 1], [11, 7], [10, 2], [11, 10], [10, 5], [8, 9]], "devacc": 77.6, "acc": 78.55}, "99_head": {"device": ["2"], "batch_size": 1000, "kfold": 5, "usepytorch": true, "task_path": "./SentEval/data/", "cache_path": "./cache/", "result_path": "./ds_top_head_wise_results/", "optim": "rmsprop", "cbatch_size": 256, "tenacity": 3, "epoch_size": 2, "model_name": "bert-base-uncased", "task": "SICKEntailment", "num_head": 99, "intv_head": 3, "total_head": 144, "location": "head", "head_size": 64, "dropout": 0, "nhid": 0, "seed": 123, "classifier": {"nhid": 0, "optim": "rmsprop", "tenacity": 3, "epoch_size": 2, "dropout": 0, "batch_size": 256}, "heads": [[1, 9], [3, 2], [1, 8], [2, 2], [5, 3], [0, 4], [2, 7], [5, 8], [2, 4], [1, 0], [0, 3], [0, 0], [4, 2], [11, 5], [0, 9], [3, 4], [1, 10], [2, 8], [2, 10], [2, 6], [5, 4], [3, 8], [11, 11], [1, 5], [1, 11], [2, 1], [1, 3], [2, 3], [7, 1], [3, 7], [2, 5], [11, 9], [4, 9], [8, 7], [10, 3], [9, 10], [6, 5], [11, 8], [1, 4], [11, 6], [8, 0], [3, 6], [4, 4], [7, 5], [3, 11], [9, 8], [1, 2], [8, 8], [6, 1], [10, 7], [0, 5], [11, 2], [8, 1], [1, 1], [0, 10], [9, 0], [2, 11], [11, 1], [3, 3], [6, 4], [1, 7], [5, 7], [6, 8], [4, 8], [11, 3], [11, 4], [4, 1], [10, 6], [7, 6], [10, 11], [4, 10], [3, 1], [10, 0], [11, 0], [0, 2], [3, 5], [10, 10], [1, 6], [3, 9], [8, 4], [6, 10], [7, 8], [6, 2], [4, 0], [9, 11], [10, 4], [6, 0], [3, 10], [7, 10], [2, 0], [10, 1], [11, 7], [10, 2], [11, 10], [10, 5], [8, 9], [5, 10], [4, 3], [10, 9]], "devacc": 78.2, "acc": 78.12}, "102_head": {"device": ["2"], "batch_size": 1000, "kfold": 5, "usepytorch": true, "task_path": "./SentEval/data/", "cache_path": "./cache/", "result_path": "./ds_top_head_wise_results/", "optim": "rmsprop", "cbatch_size": 256, "tenacity": 3, "epoch_size": 2, "model_name": "bert-base-uncased", "task": "SICKEntailment", "num_head": 102, "intv_head": 3, "total_head": 144, "location": "head", "head_size": 64, "dropout": 0, "nhid": 0, "seed": 123, "classifier": {"nhid": 0, "optim": "rmsprop", "tenacity": 3, "epoch_size": 2, "dropout": 0, "batch_size": 256}, "heads": [[1, 9], [3, 2], [1, 8], [2, 2], [5, 3], [0, 4], [2, 7], [5, 8], [2, 4], [1, 0], [0, 3], [0, 0], [4, 2], [11, 5], [0, 9], [3, 4], [1, 10], [2, 8], [2, 10], [2, 6], [5, 4], [3, 8], [11, 11], [1, 5], [1, 11], [2, 1], [1, 3], [2, 3], [7, 1], [3, 7], [2, 5], [11, 9], [4, 9], [8, 7], [10, 3], [9, 10], [6, 5], [11, 8], [1, 4], [11, 6], [8, 0], [3, 6], [4, 4], [7, 5], [3, 11], [9, 8], [1, 2], [8, 8], [6, 1], [10, 7], [0, 5], [11, 2], [8, 1], [1, 1], [0, 10], [9, 0], [2, 11], [11, 1], [3, 3], [6, 4], [1, 7], [5, 7], [6, 8], [4, 8], [11, 3], [11, 4], [4, 1], [10, 6], [7, 6], [10, 11], [4, 10], [3, 1], [10, 0], [11, 0], [0, 2], [3, 5], [10, 10], [1, 6], [3, 9], [8, 4], [6, 10], [7, 8], [6, 2], [4, 0], [9, 11], [10, 4], [6, 0], [3, 10], [7, 10], [2, 0], [10, 1], [11, 7], [10, 2], [11, 10], [10, 5], [8, 9], [5, 10], [4, 3], [10, 9], [7, 0], [5, 0], [10, 8]], "devacc": 78.8, "acc": 76.46}, "105_head": {"device": ["2"], "batch_size": 1000, "kfold": 5, "usepytorch": true, "task_path": "./SentEval/data/", "cache_path": "./cache/", "result_path": "./ds_top_head_wise_results/", "optim": "rmsprop", "cbatch_size": 256, "tenacity": 3, "epoch_size": 2, "model_name": "bert-base-uncased", "task": "SICKEntailment", "num_head": 105, "intv_head": 3, "total_head": 144, "location": "head", "head_size": 64, "dropout": 0, "nhid": 0, "seed": 123, "classifier": {"nhid": 0, "optim": "rmsprop", "tenacity": 3, "epoch_size": 2, "dropout": 0, "batch_size": 256}, "heads": [[1, 9], [3, 2], [1, 8], [2, 2], [5, 3], [0, 4], [2, 7], [5, 8], [2, 4], [1, 0], [0, 3], [0, 0], [4, 2], [11, 5], [0, 9], [3, 4], [1, 10], [2, 8], [2, 10], [2, 6], [5, 4], [3, 8], [11, 11], [1, 5], [1, 11], [2, 1], [1, 3], [2, 3], [7, 1], [3, 7], [2, 5], [11, 9], [4, 9], [8, 7], [10, 3], [9, 10], [6, 5], [11, 8], [1, 4], [11, 6], [8, 0], [3, 6], [4, 4], [7, 5], [3, 11], [9, 8], [1, 2], [8, 8], [6, 1], [10, 7], [0, 5], [11, 2], [8, 1], [1, 1], [0, 10], [9, 0], [2, 11], [11, 1], [3, 3], [6, 4], [1, 7], [5, 7], [6, 8], [4, 8], [11, 3], [11, 4], [4, 1], [10, 6], [7, 6], [10, 11], [4, 10], [3, 1], [10, 0], [11, 0], [0, 2], [3, 5], [10, 10], [1, 6], [3, 9], [8, 4], [6, 10], [7, 8], [6, 2], [4, 0], [9, 11], [10, 4], [6, 0], [3, 10], [7, 10], [2, 0], [10, 1], [11, 7], [10, 2], [11, 10], [10, 5], [8, 9], [5, 10], [4, 3], [10, 9], [7, 0], [5, 0], [10, 8], [0, 8], [2, 9], [9, 7]], "devacc": 80.6, "acc": 80.66}, "108_head": {"device": ["2"], "batch_size": 1000, "kfold": 5, "usepytorch": true, "task_path": "./SentEval/data/", "cache_path": "./cache/", "result_path": "./ds_top_head_wise_results/", "optim": "rmsprop", "cbatch_size": 256, "tenacity": 3, "epoch_size": 2, "model_name": "bert-base-uncased", "task": "SICKEntailment", "num_head": 108, "intv_head": 3, "total_head": 144, "location": "head", "head_size": 64, "dropout": 0, "nhid": 0, "seed": 123, "classifier": {"nhid": 0, "optim": "rmsprop", "tenacity": 3, "epoch_size": 2, "dropout": 0, "batch_size": 256}, "heads": [[1, 9], [3, 2], [1, 8], [2, 2], [5, 3], [0, 4], [2, 7], [5, 8], [2, 4], [1, 0], [0, 3], [0, 0], [4, 2], [11, 5], [0, 9], [3, 4], [1, 10], [2, 8], [2, 10], [2, 6], [5, 4], [3, 8], [11, 11], [1, 5], [1, 11], [2, 1], [1, 3], [2, 3], [7, 1], [3, 7], [2, 5], [11, 9], [4, 9], [8, 7], [10, 3], [9, 10], [6, 5], [11, 8], [1, 4], [11, 6], [8, 0], [3, 6], [4, 4], [7, 5], [3, 11], [9, 8], [1, 2], [8, 8], [6, 1], [10, 7], [0, 5], [11, 2], [8, 1], [1, 1], [0, 10], [9, 0], [2, 11], [11, 1], [3, 3], [6, 4], [1, 7], [5, 7], [6, 8], [4, 8], [11, 3], [11, 4], [4, 1], [10, 6], [7, 6], [10, 11], [4, 10], [3, 1], [10, 0], [11, 0], [0, 2], [3, 5], [10, 10], [1, 6], [3, 9], [8, 4], [6, 10], [7, 8], [6, 2], [4, 0], [9, 11], [10, 4], [6, 0], [3, 10], [7, 10], [2, 0], [10, 1], [11, 7], [10, 2], [11, 10], [10, 5], [8, 9], [5, 10], [4, 3], [10, 9], [7, 0], [5, 0], [10, 8], [0, 8], [2, 9], [9, 7], [9, 5], [6, 7], [9, 3]], "devacc": 80.4, "acc": 78.85}, "111_head": {"device": ["2"], "batch_size": 1000, "kfold": 5, "usepytorch": true, "task_path": "./SentEval/data/", "cache_path": "./cache/", "result_path": "./ds_top_head_wise_results/", "optim": "rmsprop", "cbatch_size": 256, "tenacity": 3, "epoch_size": 2, "model_name": "bert-base-uncased", "task": "SICKEntailment", "num_head": 111, "intv_head": 3, "total_head": 144, "location": "head", "head_size": 64, "dropout": 0, "nhid": 0, "seed": 123, "classifier": {"nhid": 0, "optim": "rmsprop", "tenacity": 3, "epoch_size": 2, "dropout": 0, "batch_size": 256}, "heads": [[1, 9], [3, 2], [1, 8], [2, 2], [5, 3], [0, 4], [2, 7], [5, 8], [2, 4], [1, 0], [0, 3], [0, 0], [4, 2], [11, 5], [0, 9], [3, 4], [1, 10], [2, 8], [2, 10], [2, 6], [5, 4], [3, 8], [11, 11], [1, 5], [1, 11], [2, 1], [1, 3], [2, 3], [7, 1], [3, 7], [2, 5], [11, 9], [4, 9], [8, 7], [10, 3], [9, 10], [6, 5], [11, 8], [1, 4], [11, 6], [8, 0], [3, 6], [4, 4], [7, 5], [3, 11], [9, 8], [1, 2], [8, 8], [6, 1], [10, 7], [0, 5], [11, 2], [8, 1], [1, 1], [0, 10], [9, 0], [2, 11], [11, 1], [3, 3], [6, 4], [1, 7], [5, 7], [6, 8], [4, 8], [11, 3], [11, 4], [4, 1], [10, 6], [7, 6], [10, 11], [4, 10], [3, 1], [10, 0], [11, 0], [0, 2], [3, 5], [10, 10], [1, 6], [3, 9], [8, 4], [6, 10], [7, 8], [6, 2], [4, 0], [9, 11], [10, 4], [6, 0], [3, 10], [7, 10], [2, 0], [10, 1], [11, 7], [10, 2], [11, 10], [10, 5], [8, 9], [5, 10], [4, 3], [10, 9], [7, 0], [5, 0], [10, 8], [0, 8], [2, 9], [9, 7], [9, 5], [6, 7], [9, 3], [9, 2], [5, 11], [5, 2]], "devacc": 80.4, "acc": 79.01}, "114_head": {"device": ["2"], "batch_size": 1000, "kfold": 5, "usepytorch": true, "task_path": "./SentEval/data/", "cache_path": "./cache/", "result_path": "./ds_top_head_wise_results/", "optim": "rmsprop", "cbatch_size": 256, "tenacity": 3, "epoch_size": 2, "model_name": "bert-base-uncased", "task": "SICKEntailment", "num_head": 114, "intv_head": 3, "total_head": 144, "location": "head", "head_size": 64, "dropout": 0, "nhid": 0, "seed": 123, "classifier": {"nhid": 0, "optim": "rmsprop", "tenacity": 3, "epoch_size": 2, "dropout": 0, "batch_size": 256}, "heads": [[1, 9], [3, 2], [1, 8], [2, 2], [5, 3], [0, 4], [2, 7], [5, 8], [2, 4], [1, 0], [0, 3], [0, 0], [4, 2], [11, 5], [0, 9], [3, 4], [1, 10], [2, 8], [2, 10], [2, 6], [5, 4], [3, 8], [11, 11], [1, 5], [1, 11], [2, 1], [1, 3], [2, 3], [7, 1], [3, 7], [2, 5], [11, 9], [4, 9], [8, 7], [10, 3], [9, 10], [6, 5], [11, 8], [1, 4], [11, 6], [8, 0], [3, 6], [4, 4], [7, 5], [3, 11], [9, 8], [1, 2], [8, 8], [6, 1], [10, 7], [0, 5], [11, 2], [8, 1], [1, 1], [0, 10], [9, 0], [2, 11], [11, 1], [3, 3], [6, 4], [1, 7], [5, 7], [6, 8], [4, 8], [11, 3], [11, 4], [4, 1], [10, 6], [7, 6], [10, 11], [4, 10], [3, 1], [10, 0], [11, 0], [0, 2], [3, 5], [10, 10], [1, 6], [3, 9], [8, 4], [6, 10], [7, 8], [6, 2], [4, 0], [9, 11], [10, 4], [6, 0], [3, 10], [7, 10], [2, 0], [10, 1], [11, 7], [10, 2], [11, 10], [10, 5], [8, 9], [5, 10], [4, 3], [10, 9], [7, 0], [5, 0], [10, 8], [0, 8], [2, 9], [9, 7], [9, 5], [6, 7], [9, 3], [9, 2], [5, 11], [5, 2], [5, 5], [9, 4], [6, 11]], "devacc": 80.6, "acc": 78.57}, "117_head": {"device": ["2"], "batch_size": 1000, "kfold": 5, "usepytorch": true, "task_path": "./SentEval/data/", "cache_path": "./cache/", "result_path": "./ds_top_head_wise_results/", "optim": "rmsprop", "cbatch_size": 256, "tenacity": 3, "epoch_size": 2, "model_name": "bert-base-uncased", "task": "SICKEntailment", "num_head": 117, "intv_head": 3, "total_head": 144, "location": "head", "head_size": 64, "dropout": 0, "nhid": 0, "seed": 123, "classifier": {"nhid": 0, "optim": "rmsprop", "tenacity": 3, "epoch_size": 2, "dropout": 0, "batch_size": 256}, "heads": [[1, 9], [3, 2], [1, 8], [2, 2], [5, 3], [0, 4], [2, 7], [5, 8], [2, 4], [1, 0], [0, 3], [0, 0], [4, 2], [11, 5], [0, 9], [3, 4], [1, 10], [2, 8], [2, 10], [2, 6], [5, 4], [3, 8], [11, 11], [1, 5], [1, 11], [2, 1], [1, 3], [2, 3], [7, 1], [3, 7], [2, 5], [11, 9], [4, 9], [8, 7], [10, 3], [9, 10], [6, 5], [11, 8], [1, 4], [11, 6], [8, 0], [3, 6], [4, 4], [7, 5], [3, 11], [9, 8], [1, 2], [8, 8], [6, 1], [10, 7], [0, 5], [11, 2], [8, 1], [1, 1], [0, 10], [9, 0], [2, 11], [11, 1], [3, 3], [6, 4], [1, 7], [5, 7], [6, 8], [4, 8], [11, 3], [11, 4], [4, 1], [10, 6], [7, 6], [10, 11], [4, 10], [3, 1], [10, 0], [11, 0], [0, 2], [3, 5], [10, 10], [1, 6], [3, 9], [8, 4], [6, 10], [7, 8], [6, 2], [4, 0], [9, 11], [10, 4], [6, 0], [3, 10], [7, 10], [2, 0], [10, 1], [11, 7], [10, 2], [11, 10], [10, 5], [8, 9], [5, 10], [4, 3], [10, 9], [7, 0], [5, 0], [10, 8], [0, 8], [2, 9], [9, 7], [9, 5], [6, 7], [9, 3], [9, 2], [5, 11], [5, 2], [5, 5], [9, 4], [6, 11], [7, 11], [8, 5], [4, 7]], "devacc": 80.0, "acc": 79.48}, "120_head": {"device": ["2"], "batch_size": 1000, "kfold": 5, "usepytorch": true, "task_path": "./SentEval/data/", "cache_path": "./cache/", "result_path": "./ds_top_head_wise_results/", "optim": "rmsprop", "cbatch_size": 256, "tenacity": 3, "epoch_size": 2, "model_name": "bert-base-uncased", "task": "SICKEntailment", "num_head": 120, "intv_head": 3, "total_head": 144, "location": "head", "head_size": 64, "dropout": 0, "nhid": 0, "seed": 123, "classifier": {"nhid": 0, "optim": "rmsprop", "tenacity": 3, "epoch_size": 2, "dropout": 0, "batch_size": 256}, "heads": [[1, 9], [3, 2], [1, 8], [2, 2], [5, 3], [0, 4], [2, 7], [5, 8], [2, 4], [1, 0], [0, 3], [0, 0], [4, 2], [11, 5], [0, 9], [3, 4], [1, 10], [2, 8], [2, 10], [2, 6], [5, 4], [3, 8], [11, 11], [1, 5], [1, 11], [2, 1], [1, 3], [2, 3], [7, 1], [3, 7], [2, 5], [11, 9], [4, 9], [8, 7], [10, 3], [9, 10], [6, 5], [11, 8], [1, 4], [11, 6], [8, 0], [3, 6], [4, 4], [7, 5], [3, 11], [9, 8], [1, 2], [8, 8], [6, 1], [10, 7], [0, 5], [11, 2], [8, 1], [1, 1], [0, 10], [9, 0], [2, 11], [11, 1], [3, 3], [6, 4], [1, 7], [5, 7], [6, 8], [4, 8], [11, 3], [11, 4], [4, 1], [10, 6], [7, 6], [10, 11], [4, 10], [3, 1], [10, 0], [11, 0], [0, 2], [3, 5], [10, 10], [1, 6], [3, 9], [8, 4], [6, 10], [7, 8], [6, 2], [4, 0], [9, 11], [10, 4], [6, 0], [3, 10], [7, 10], [2, 0], [10, 1], [11, 7], [10, 2], [11, 10], [10, 5], [8, 9], [5, 10], [4, 3], [10, 9], [7, 0], [5, 0], [10, 8], [0, 8], [2, 9], [9, 7], [9, 5], [6, 7], [9, 3], [9, 2], [5, 11], [5, 2], [5, 5], [9, 4], [6, 11], [7, 11], [8, 5], [4, 7], [5, 9], [3, 0], [4, 11]], "devacc": 79.2, "acc": 79.16}, "123_head": {"device": ["2"], "batch_size": 1000, "kfold": 5, "usepytorch": true, "task_path": "./SentEval/data/", "cache_path": "./cache/", "result_path": "./ds_top_head_wise_results/", "optim": "rmsprop", "cbatch_size": 256, "tenacity": 3, "epoch_size": 2, "model_name": "bert-base-uncased", "task": "SICKEntailment", "num_head": 123, "intv_head": 3, "total_head": 144, "location": "head", "head_size": 64, "dropout": 0, "nhid": 0, "seed": 123, "classifier": {"nhid": 0, "optim": "rmsprop", "tenacity": 3, "epoch_size": 2, "dropout": 0, "batch_size": 256}, "heads": [[1, 9], [3, 2], [1, 8], [2, 2], [5, 3], [0, 4], [2, 7], [5, 8], [2, 4], [1, 0], [0, 3], [0, 0], [4, 2], [11, 5], [0, 9], [3, 4], [1, 10], [2, 8], [2, 10], [2, 6], [5, 4], [3, 8], [11, 11], [1, 5], [1, 11], [2, 1], [1, 3], [2, 3], [7, 1], [3, 7], [2, 5], [11, 9], [4, 9], [8, 7], [10, 3], [9, 10], [6, 5], [11, 8], [1, 4], [11, 6], [8, 0], [3, 6], [4, 4], [7, 5], [3, 11], [9, 8], [1, 2], [8, 8], [6, 1], [10, 7], [0, 5], [11, 2], [8, 1], [1, 1], [0, 10], [9, 0], [2, 11], [11, 1], [3, 3], [6, 4], [1, 7], [5, 7], [6, 8], [4, 8], [11, 3], [11, 4], [4, 1], [10, 6], [7, 6], [10, 11], [4, 10], [3, 1], [10, 0], [11, 0], [0, 2], [3, 5], [10, 10], [1, 6], [3, 9], [8, 4], [6, 10], [7, 8], [6, 2], [4, 0], [9, 11], [10, 4], [6, 0], [3, 10], [7, 10], [2, 0], [10, 1], [11, 7], [10, 2], [11, 10], [10, 5], [8, 9], [5, 10], [4, 3], [10, 9], [7, 0], [5, 0], [10, 8], [0, 8], [2, 9], [9, 7], [9, 5], [6, 7], [9, 3], [9, 2], [5, 11], [5, 2], [5, 5], [9, 4], [6, 11], [7, 11], [8, 5], [4, 7], [5, 9], [3, 0], [4, 11], [9, 9], [8, 3], [4, 5]], "devacc": 79.6, "acc": 78.71}, "126_head": {"device": ["2"], "batch_size": 1000, "kfold": 5, "usepytorch": true, "task_path": "./SentEval/data/", "cache_path": "./cache/", "result_path": "./ds_top_head_wise_results/", "optim": "rmsprop", "cbatch_size": 256, "tenacity": 3, "epoch_size": 2, "model_name": "bert-base-uncased", "task": "SICKEntailment", "num_head": 126, "intv_head": 3, "total_head": 144, "location": "head", "head_size": 64, "dropout": 0, "nhid": 0, "seed": 123, "classifier": {"nhid": 0, "optim": "rmsprop", "tenacity": 3, "epoch_size": 2, "dropout": 0, "batch_size": 256}, "heads": [[1, 9], [3, 2], [1, 8], [2, 2], [5, 3], [0, 4], [2, 7], [5, 8], [2, 4], [1, 0], [0, 3], [0, 0], [4, 2], [11, 5], [0, 9], [3, 4], [1, 10], [2, 8], [2, 10], [2, 6], [5, 4], [3, 8], [11, 11], [1, 5], [1, 11], [2, 1], [1, 3], [2, 3], [7, 1], [3, 7], [2, 5], [11, 9], [4, 9], [8, 7], [10, 3], [9, 10], [6, 5], [11, 8], [1, 4], [11, 6], [8, 0], [3, 6], [4, 4], [7, 5], [3, 11], [9, 8], [1, 2], [8, 8], [6, 1], [10, 7], [0, 5], [11, 2], [8, 1], [1, 1], [0, 10], [9, 0], [2, 11], [11, 1], [3, 3], [6, 4], [1, 7], [5, 7], [6, 8], [4, 8], [11, 3], [11, 4], [4, 1], [10, 6], [7, 6], [10, 11], [4, 10], [3, 1], [10, 0], [11, 0], [0, 2], [3, 5], [10, 10], [1, 6], [3, 9], [8, 4], [6, 10], [7, 8], [6, 2], [4, 0], [9, 11], [10, 4], [6, 0], [3, 10], [7, 10], [2, 0], [10, 1], [11, 7], [10, 2], [11, 10], [10, 5], [8, 9], [5, 10], [4, 3], [10, 9], [7, 0], [5, 0], [10, 8], [0, 8], [2, 9], [9, 7], [9, 5], [6, 7], [9, 3], [9, 2], [5, 11], [5, 2], [5, 5], [9, 4], [6, 11], [7, 11], [8, 5], [4, 7], [5, 9], [3, 0], [4, 11], [9, 9], [8, 3], [4, 5], [7, 2], [9, 6], [6, 6]], "devacc": 79.8, "acc": 79.3}, "129_head": {"device": ["2"], "batch_size": 1000, "kfold": 5, "usepytorch": true, "task_path": "./SentEval/data/", "cache_path": "./cache/", "result_path": "./ds_top_head_wise_results/", "optim": "rmsprop", "cbatch_size": 256, "tenacity": 3, "epoch_size": 2, "model_name": "bert-base-uncased", "task": "SICKEntailment", "num_head": 129, "intv_head": 3, "total_head": 144, "location": "head", "head_size": 64, "dropout": 0, "nhid": 0, "seed": 123, "classifier": {"nhid": 0, "optim": "rmsprop", "tenacity": 3, "epoch_size": 2, "dropout": 0, "batch_size": 256}, "heads": [[1, 9], [3, 2], [1, 8], [2, 2], [5, 3], [0, 4], [2, 7], [5, 8], [2, 4], [1, 0], [0, 3], [0, 0], [4, 2], [11, 5], [0, 9], [3, 4], [1, 10], [2, 8], [2, 10], [2, 6], [5, 4], [3, 8], [11, 11], [1, 5], [1, 11], [2, 1], [1, 3], [2, 3], [7, 1], [3, 7], [2, 5], [11, 9], [4, 9], [8, 7], [10, 3], [9, 10], [6, 5], [11, 8], [1, 4], [11, 6], [8, 0], [3, 6], [4, 4], [7, 5], [3, 11], [9, 8], [1, 2], [8, 8], [6, 1], [10, 7], [0, 5], [11, 2], [8, 1], [1, 1], [0, 10], [9, 0], [2, 11], [11, 1], [3, 3], [6, 4], [1, 7], [5, 7], [6, 8], [4, 8], [11, 3], [11, 4], [4, 1], [10, 6], [7, 6], [10, 11], [4, 10], [3, 1], [10, 0], [11, 0], [0, 2], [3, 5], [10, 10], [1, 6], [3, 9], [8, 4], [6, 10], [7, 8], [6, 2], [4, 0], [9, 11], [10, 4], [6, 0], [3, 10], [7, 10], [2, 0], [10, 1], [11, 7], [10, 2], [11, 10], [10, 5], [8, 9], [5, 10], [4, 3], [10, 9], [7, 0], [5, 0], [10, 8], [0, 8], [2, 9], [9, 7], [9, 5], [6, 7], [9, 3], [9, 2], [5, 11], [5, 2], [5, 5], [9, 4], [6, 11], [7, 11], [8, 5], [4, 7], [5, 9], [3, 0], [4, 11], [9, 9], [8, 3], [4, 5], [7, 2], [9, 6], [6, 6], [5, 6], [0, 1], [7, 9]], "devacc": 78.4, "acc": 79.56}, "132_head": {"device": ["2"], "batch_size": 1000, "kfold": 5, "usepytorch": true, "task_path": "./SentEval/data/", "cache_path": "./cache/", "result_path": "./ds_top_head_wise_results/", "optim": "rmsprop", "cbatch_size": 256, "tenacity": 3, "epoch_size": 2, "model_name": "bert-base-uncased", "task": "SICKEntailment", "num_head": 132, "intv_head": 3, "total_head": 144, "location": "head", "head_size": 64, "dropout": 0, "nhid": 0, "seed": 123, "classifier": {"nhid": 0, "optim": "rmsprop", "tenacity": 3, "epoch_size": 2, "dropout": 0, "batch_size": 256}, "heads": [[1, 9], [3, 2], [1, 8], [2, 2], [5, 3], [0, 4], [2, 7], [5, 8], [2, 4], [1, 0], [0, 3], [0, 0], [4, 2], [11, 5], [0, 9], [3, 4], [1, 10], [2, 8], [2, 10], [2, 6], [5, 4], [3, 8], [11, 11], [1, 5], [1, 11], [2, 1], [1, 3], [2, 3], [7, 1], [3, 7], [2, 5], [11, 9], [4, 9], [8, 7], [10, 3], [9, 10], [6, 5], [11, 8], [1, 4], [11, 6], [8, 0], [3, 6], [4, 4], [7, 5], [3, 11], [9, 8], [1, 2], [8, 8], [6, 1], [10, 7], [0, 5], [11, 2], [8, 1], [1, 1], [0, 10], [9, 0], [2, 11], [11, 1], [3, 3], [6, 4], [1, 7], [5, 7], [6, 8], [4, 8], [11, 3], [11, 4], [4, 1], [10, 6], [7, 6], [10, 11], [4, 10], [3, 1], [10, 0], [11, 0], [0, 2], [3, 5], [10, 10], [1, 6], [3, 9], [8, 4], [6, 10], [7, 8], [6, 2], [4, 0], [9, 11], [10, 4], [6, 0], [3, 10], [7, 10], [2, 0], [10, 1], [11, 7], [10, 2], [11, 10], [10, 5], [8, 9], [5, 10], [4, 3], [10, 9], [7, 0], [5, 0], [10, 8], [0, 8], [2, 9], [9, 7], [9, 5], [6, 7], [9, 3], [9, 2], [5, 11], [5, 2], [5, 5], [9, 4], [6, 11], [7, 11], [8, 5], [4, 7], [5, 9], [3, 0], [4, 11], [9, 9], [8, 3], [4, 5], [7, 2], [9, 6], [6, 6], [5, 6], [0, 1], [7, 9], [9, 1], [0, 7], [6, 9]], "devacc": 79.6, "acc": 79.48}, "135_head": {"device": ["2"], "batch_size": 1000, "kfold": 5, "usepytorch": true, "task_path": "./SentEval/data/", "cache_path": "./cache/", "result_path": "./ds_top_head_wise_results/", "optim": "rmsprop", "cbatch_size": 256, "tenacity": 3, "epoch_size": 2, "model_name": "bert-base-uncased", "task": "SICKEntailment", "num_head": 135, "intv_head": 3, "total_head": 144, "location": "head", "head_size": 64, "dropout": 0, "nhid": 0, "seed": 123, "classifier": {"nhid": 0, "optim": "rmsprop", "tenacity": 3, "epoch_size": 2, "dropout": 0, "batch_size": 256}, "heads": [[1, 9], [3, 2], [1, 8], [2, 2], [5, 3], [0, 4], [2, 7], [5, 8], [2, 4], [1, 0], [0, 3], [0, 0], [4, 2], [11, 5], [0, 9], [3, 4], [1, 10], [2, 8], [2, 10], [2, 6], [5, 4], [3, 8], [11, 11], [1, 5], [1, 11], [2, 1], [1, 3], [2, 3], [7, 1], [3, 7], [2, 5], [11, 9], [4, 9], [8, 7], [10, 3], [9, 10], [6, 5], [11, 8], [1, 4], [11, 6], [8, 0], [3, 6], [4, 4], [7, 5], [3, 11], [9, 8], [1, 2], [8, 8], [6, 1], [10, 7], [0, 5], [11, 2], [8, 1], [1, 1], [0, 10], [9, 0], [2, 11], [11, 1], [3, 3], [6, 4], [1, 7], [5, 7], [6, 8], [4, 8], [11, 3], [11, 4], [4, 1], [10, 6], [7, 6], [10, 11], [4, 10], [3, 1], [10, 0], [11, 0], [0, 2], [3, 5], [10, 10], [1, 6], [3, 9], [8, 4], [6, 10], [7, 8], [6, 2], [4, 0], [9, 11], [10, 4], [6, 0], [3, 10], [7, 10], [2, 0], [10, 1], [11, 7], [10, 2], [11, 10], [10, 5], [8, 9], [5, 10], [4, 3], [10, 9], [7, 0], [5, 0], [10, 8], [0, 8], [2, 9], [9, 7], [9, 5], [6, 7], [9, 3], [9, 2], [5, 11], [5, 2], [5, 5], [9, 4], [6, 11], [7, 11], [8, 5], [4, 7], [5, 9], [3, 0], [4, 11], [9, 9], [8, 3], [4, 5], [7, 2], [9, 6], [6, 6], [5, 6], [0, 1], [7, 9], [9, 1], [0, 7], [6, 9], [8, 11], [7, 3], [6, 3]], "devacc": 79.0, "acc": 79.54}, "138_head": {"device": ["2"], "batch_size": 1000, "kfold": 5, "usepytorch": true, "task_path": "./SentEval/data/", "cache_path": "./cache/", "result_path": "./ds_top_head_wise_results/", "optim": "rmsprop", "cbatch_size": 256, "tenacity": 3, "epoch_size": 2, "model_name": "bert-base-uncased", "task": "SICKEntailment", "num_head": 138, "intv_head": 3, "total_head": 144, "location": "head", "head_size": 64, "dropout": 0, "nhid": 0, "seed": 123, "classifier": {"nhid": 0, "optim": "rmsprop", "tenacity": 3, "epoch_size": 2, "dropout": 0, "batch_size": 256}, "heads": [[1, 9], [3, 2], [1, 8], [2, 2], [5, 3], [0, 4], [2, 7], [5, 8], [2, 4], [1, 0], [0, 3], [0, 0], [4, 2], [11, 5], [0, 9], [3, 4], [1, 10], [2, 8], [2, 10], [2, 6], [5, 4], [3, 8], [11, 11], [1, 5], [1, 11], [2, 1], [1, 3], [2, 3], [7, 1], [3, 7], [2, 5], [11, 9], [4, 9], [8, 7], [10, 3], [9, 10], [6, 5], [11, 8], [1, 4], [11, 6], [8, 0], [3, 6], [4, 4], [7, 5], [3, 11], [9, 8], [1, 2], [8, 8], [6, 1], [10, 7], [0, 5], [11, 2], [8, 1], [1, 1], [0, 10], [9, 0], [2, 11], [11, 1], [3, 3], [6, 4], [1, 7], [5, 7], [6, 8], [4, 8], [11, 3], [11, 4], [4, 1], [10, 6], [7, 6], [10, 11], [4, 10], [3, 1], [10, 0], [11, 0], [0, 2], [3, 5], [10, 10], [1, 6], [3, 9], [8, 4], [6, 10], [7, 8], [6, 2], [4, 0], [9, 11], [10, 4], [6, 0], [3, 10], [7, 10], [2, 0], [10, 1], [11, 7], [10, 2], [11, 10], [10, 5], [8, 9], [5, 10], [4, 3], [10, 9], [7, 0], [5, 0], [10, 8], [0, 8], [2, 9], [9, 7], [9, 5], [6, 7], [9, 3], [9, 2], [5, 11], [5, 2], [5, 5], [9, 4], [6, 11], [7, 11], [8, 5], [4, 7], [5, 9], [3, 0], [4, 11], [9, 9], [8, 3], [4, 5], [7, 2], [9, 6], [6, 6], [5, 6], [0, 1], [7, 9], [9, 1], [0, 7], [6, 9], [8, 11], [7, 3], [6, 3], [4, 6], [7, 7], [8, 2]], "devacc": 79.8, "acc": 78.99}, "141_head": {"device": ["2"], "batch_size": 1000, "kfold": 5, "usepytorch": true, "task_path": "./SentEval/data/", "cache_path": "./cache/", "result_path": "./ds_top_head_wise_results/", "optim": "rmsprop", "cbatch_size": 256, "tenacity": 3, "epoch_size": 2, "model_name": "bert-base-uncased", "task": "SICKEntailment", "num_head": 141, "intv_head": 3, "total_head": 144, "location": "head", "head_size": 64, "dropout": 0, "nhid": 0, "seed": 123, "classifier": {"nhid": 0, "optim": "rmsprop", "tenacity": 3, "epoch_size": 2, "dropout": 0, "batch_size": 256}, "heads": [[1, 9], [3, 2], [1, 8], [2, 2], [5, 3], [0, 4], [2, 7], [5, 8], [2, 4], [1, 0], [0, 3], [0, 0], [4, 2], [11, 5], [0, 9], [3, 4], [1, 10], [2, 8], [2, 10], [2, 6], [5, 4], [3, 8], [11, 11], [1, 5], [1, 11], [2, 1], [1, 3], [2, 3], [7, 1], [3, 7], [2, 5], [11, 9], [4, 9], [8, 7], [10, 3], [9, 10], [6, 5], [11, 8], [1, 4], [11, 6], [8, 0], [3, 6], [4, 4], [7, 5], [3, 11], [9, 8], [1, 2], [8, 8], [6, 1], [10, 7], [0, 5], [11, 2], [8, 1], [1, 1], [0, 10], [9, 0], [2, 11], [11, 1], [3, 3], [6, 4], [1, 7], [5, 7], [6, 8], [4, 8], [11, 3], [11, 4], [4, 1], [10, 6], [7, 6], [10, 11], [4, 10], [3, 1], [10, 0], [11, 0], [0, 2], [3, 5], [10, 10], [1, 6], [3, 9], [8, 4], [6, 10], [7, 8], [6, 2], [4, 0], [9, 11], [10, 4], [6, 0], [3, 10], [7, 10], [2, 0], [10, 1], [11, 7], [10, 2], [11, 10], [10, 5], [8, 9], [5, 10], [4, 3], [10, 9], [7, 0], [5, 0], [10, 8], [0, 8], [2, 9], [9, 7], [9, 5], [6, 7], [9, 3], [9, 2], [5, 11], [5, 2], [5, 5], [9, 4], [6, 11], [7, 11], [8, 5], [4, 7], [5, 9], [3, 0], [4, 11], [9, 9], [8, 3], [4, 5], [7, 2], [9, 6], [6, 6], [5, 6], [0, 1], [7, 9], [9, 1], [0, 7], [6, 9], [8, 11], [7, 3], [6, 3], [4, 6], [7, 7], [8, 2], [7, 4], [0, 11], [0, 6]], "devacc": 80.2, "acc": 78.93}, "144_head": {"device": ["2"], "batch_size": 1000, "kfold": 5, "usepytorch": true, "task_path": "./SentEval/data/", "cache_path": "./cache/", "result_path": "./ds_top_head_wise_results/", "optim": "rmsprop", "cbatch_size": 256, "tenacity": 3, "epoch_size": 2, "model_name": "bert-base-uncased", "task": "SICKEntailment", "num_head": 144, "intv_head": 3, "total_head": 144, "location": "head", "head_size": 64, "dropout": 0, "nhid": 0, "seed": 123, "classifier": {"nhid": 0, "optim": "rmsprop", "tenacity": 3, "epoch_size": 2, "dropout": 0, "batch_size": 256}, "heads": [[1, 9], [3, 2], [1, 8], [2, 2], [5, 3], [0, 4], [2, 7], [5, 8], [2, 4], [1, 0], [0, 3], [0, 0], [4, 2], [11, 5], [0, 9], [3, 4], [1, 10], [2, 8], [2, 10], [2, 6], [5, 4], [3, 8], [11, 11], [1, 5], [1, 11], [2, 1], [1, 3], [2, 3], [7, 1], [3, 7], [2, 5], [11, 9], [4, 9], [8, 7], [10, 3], [9, 10], [6, 5], [11, 8], [1, 4], [11, 6], [8, 0], [3, 6], [4, 4], [7, 5], [3, 11], [9, 8], [1, 2], [8, 8], [6, 1], [10, 7], [0, 5], [11, 2], [8, 1], [1, 1], [0, 10], [9, 0], [2, 11], [11, 1], [3, 3], [6, 4], [1, 7], [5, 7], [6, 8], [4, 8], [11, 3], [11, 4], [4, 1], [10, 6], [7, 6], [10, 11], [4, 10], [3, 1], [10, 0], [11, 0], [0, 2], [3, 5], [10, 10], [1, 6], [3, 9], [8, 4], [6, 10], [7, 8], [6, 2], [4, 0], [9, 11], [10, 4], [6, 0], [3, 10], [7, 10], [2, 0], [10, 1], [11, 7], [10, 2], [11, 10], [10, 5], [8, 9], [5, 10], [4, 3], [10, 9], [7, 0], [5, 0], [10, 8], [0, 8], [2, 9], [9, 7], [9, 5], [6, 7], [9, 3], [9, 2], [5, 11], [5, 2], [5, 5], [9, 4], [6, 11], [7, 11], [8, 5], [4, 7], [5, 9], [3, 0], [4, 11], [9, 9], [8, 3], [4, 5], [7, 2], [9, 6], [6, 6], [5, 6], [0, 1], [7, 9], [9, 1], [0, 7], [6, 9], [8, 11], [7, 3], [6, 3], [4, 6], [7, 7], [8, 2], [7, 4], [0, 11], [0, 6], [8, 10], [8, 6], [5, 1]], "devacc": 80.0, "acc": 78.95}, "1_head": {"device": ["2"], "batch_size": 1000, "kfold": 5, "usepytorch": true, "task_path": "./SentEval/data/", "cache_path": "./cache/", "result_path": "./ds_top_head_wise_results/", "optim": "rmsprop", "cbatch_size": 256, "tenacity": 3, "epoch_size": 2, "model_name": "bert-base-uncased", "task": "SICKEntailment", "num_head": 1, "intv_head": 1, "total_head": 40, "location": "head", "head_size": 64, "dropout": 0, "nhid": 0, "seed": 123, "classifier": {"nhid": 0, "optim": "rmsprop", "tenacity": 3, "epoch_size": 2, "dropout": 0, "batch_size": 256}, "heads": [[1, 9]], "devacc": 74.2, "acc": 73.82}, "2_head": {"device": ["2"], "batch_size": 1000, "kfold": 5, "usepytorch": true, "task_path": "./SentEval/data/", "cache_path": "./cache/", "result_path": "./ds_top_head_wise_results/", "optim": "rmsprop", "cbatch_size": 256, "tenacity": 3, "epoch_size": 2, "model_name": "bert-base-uncased", "task": "SICKEntailment", "num_head": 2, "intv_head": 1, "total_head": 40, "location": "head", "head_size": 64, "dropout": 0, "nhid": 0, "seed": 123, "classifier": {"nhid": 0, "optim": "rmsprop", "tenacity": 3, "epoch_size": 2, "dropout": 0, "batch_size": 256}, "heads": [[1, 9], [3, 2]], "devacc": 75.4, "acc": 75.52}, "4_head": {"device": ["2"], "batch_size": 1000, "kfold": 5, "usepytorch": true, "task_path": "./SentEval/data/", "cache_path": "./cache/", "result_path": "./ds_top_head_wise_results/", "optim": "rmsprop", "cbatch_size": 256, "tenacity": 3, "epoch_size": 2, "model_name": "bert-base-uncased", "task": "SICKEntailment", "num_head": 4, "intv_head": 1, "total_head": 40, "location": "head", "head_size": 64, "dropout": 0, "nhid": 0, "seed": 123, "classifier": {"nhid": 0, "optim": "rmsprop", "tenacity": 3, "epoch_size": 2, "dropout": 0, "batch_size": 256}, "heads": [[1, 9], [3, 2], [1, 8], [2, 2]], "devacc": 76.8, "acc": 77.15}, "5_head": {"device": ["2"], "batch_size": 1000, "kfold": 5, "usepytorch": true, "task_path": "./SentEval/data/", "cache_path": "./cache/", "result_path": "./ds_top_head_wise_results/", "optim": "rmsprop", "cbatch_size": 256, "tenacity": 3, "epoch_size": 2, "model_name": "bert-base-uncased", "task": "SICKEntailment", "num_head": 5, "intv_head": 1, "total_head": 40, "location": "head", "head_size": 64, "dropout": 0, "nhid": 0, "seed": 123, "classifier": {"nhid": 0, "optim": "rmsprop", "tenacity": 3, "epoch_size": 2, "dropout": 0, "batch_size": 256}, "heads": [[1, 9], [3, 2], [1, 8], [2, 2], [5, 3]], "devacc": 78.6, "acc": 78.36}, "7_head": {"device": ["2"], "batch_size": 1000, "kfold": 5, "usepytorch": true, "task_path": "./SentEval/data/", "cache_path": "./cache/", "result_path": "./ds_top_head_wise_results/", "optim": "rmsprop", "cbatch_size": 256, "tenacity": 3, "epoch_size": 2, "model_name": "bert-base-uncased", "task": "SICKEntailment", "num_head": 7, "intv_head": 1, "total_head": 40, "location": "head", "head_size": 64, "dropout": 0, "nhid": 0, "seed": 123, "classifier": {"nhid": 0, "optim": "rmsprop", "tenacity": 3, "epoch_size": 2, "dropout": 0, "batch_size": 256}, "heads": [[1, 9], [3, 2], [1, 8], [2, 2], [5, 3], [0, 4], [2, 7]], "devacc": 80.4, "acc": 78.3}, "8_head": {"device": ["2"], "batch_size": 1000, "kfold": 5, "usepytorch": true, "task_path": "./SentEval/data/", "cache_path": "./cache/", "result_path": "./ds_top_head_wise_results/", "optim": "rmsprop", "cbatch_size": 256, "tenacity": 3, "epoch_size": 2, "model_name": "bert-base-uncased", "task": "SICKEntailment", "num_head": 8, "intv_head": 1, "total_head": 40, "location": "head", "head_size": 64, "dropout": 0, "nhid": 0, "seed": 123, "classifier": {"nhid": 0, "optim": "rmsprop", "tenacity": 3, "epoch_size": 2, "dropout": 0, "batch_size": 256}, "heads": [[1, 9], [3, 2], [1, 8], [2, 2], [5, 3], [0, 4], [2, 7], [5, 8]], "devacc": 79.8, "acc": 77.94}, "10_head": {"device": ["2"], "batch_size": 1000, "kfold": 5, "usepytorch": true, "task_path": "./SentEval/data/", "cache_path": "./cache/", "result_path": "./ds_top_head_wise_results/", "optim": "rmsprop", "cbatch_size": 256, "tenacity": 3, "epoch_size": 2, "model_name": "bert-base-uncased", "task": "SICKEntailment", "num_head": 10, "intv_head": 1, "total_head": 40, "location": "head", "head_size": 64, "dropout": 0, "nhid": 0, "seed": 123, "classifier": {"nhid": 0, "optim": "rmsprop", "tenacity": 3, "epoch_size": 2, "dropout": 0, "batch_size": 256}, "heads": [[1, 9], [3, 2], [1, 8], [2, 2], [5, 3], [0, 4], [2, 7], [5, 8], [2, 4], [1, 0]], "devacc": 80.2, "acc": 78.12}, "11_head": {"device": ["2"], "batch_size": 1000, "kfold": 5, "usepytorch": true, "task_path": "./SentEval/data/", "cache_path": "./cache/", "result_path": "./ds_top_head_wise_results/", "optim": "rmsprop", "cbatch_size": 256, "tenacity": 3, "epoch_size": 2, "model_name": "bert-base-uncased", "task": "SICKEntailment", "num_head": 11, "intv_head": 1, "total_head": 40, "location": "head", "head_size": 64, "dropout": 0, "nhid": 0, "seed": 123, "classifier": {"nhid": 0, "optim": "rmsprop", "tenacity": 3, "epoch_size": 2, "dropout": 0, "batch_size": 256}, "heads": [[1, 9], [3, 2], [1, 8], [2, 2], [5, 3], [0, 4], [2, 7], [5, 8], [2, 4], [1, 0], [0, 3]], "devacc": 79.8, "acc": 78.45}, "13_head": {"device": ["2"], "batch_size": 1000, "kfold": 5, "usepytorch": true, "task_path": "./SentEval/data/", "cache_path": "./cache/", "result_path": "./ds_top_head_wise_results/", "optim": "rmsprop", "cbatch_size": 256, "tenacity": 3, "epoch_size": 2, "model_name": "bert-base-uncased", "task": "SICKEntailment", "num_head": 13, "intv_head": 1, "total_head": 40, "location": "head", "head_size": 64, "dropout": 0, "nhid": 0, "seed": 123, "classifier": {"nhid": 0, "optim": "rmsprop", "tenacity": 3, "epoch_size": 2, "dropout": 0, "batch_size": 256}, "heads": [[1, 9], [3, 2], [1, 8], [2, 2], [5, 3], [0, 4], [2, 7], [5, 8], [2, 4], [1, 0], [0, 3], [0, 0], [4, 2]], "devacc": 80.8, "acc": 78.28}, "14_head": {"device": ["2"], "batch_size": 1000, "kfold": 5, "usepytorch": true, "task_path": "./SentEval/data/", "cache_path": "./cache/", "result_path": "./ds_top_head_wise_results/", "optim": "rmsprop", "cbatch_size": 256, "tenacity": 3, "epoch_size": 2, "model_name": "bert-base-uncased", "task": "SICKEntailment", "num_head": 14, "intv_head": 1, "total_head": 40, "location": "head", "head_size": 64, "dropout": 0, "nhid": 0, "seed": 123, "classifier": {"nhid": 0, "optim": "rmsprop", "tenacity": 3, "epoch_size": 2, "dropout": 0, "batch_size": 256}, "heads": [[1, 9], [3, 2], [1, 8], [2, 2], [5, 3], [0, 4], [2, 7], [5, 8], [2, 4], [1, 0], [0, 3], [0, 0], [4, 2], [11, 5]], "devacc": 80.4, "acc": 78.85}, "16_head": {"device": ["2"], "batch_size": 1000, "kfold": 5, "usepytorch": true, "task_path": "./SentEval/data/", "cache_path": "./cache/", "result_path": "./ds_top_head_wise_results/", "optim": "rmsprop", "cbatch_size": 256, "tenacity": 3, "epoch_size": 2, "model_name": "bert-base-uncased", "task": "SICKEntailment", "num_head": 16, "intv_head": 1, "total_head": 40, "location": "head", "head_size": 64, "dropout": 0, "nhid": 0, "seed": 123, "classifier": {"nhid": 0, "optim": "rmsprop", "tenacity": 3, "epoch_size": 2, "dropout": 0, "batch_size": 256}, "heads": [[1, 9], [3, 2], [1, 8], [2, 2], [5, 3], [0, 4], [2, 7], [5, 8], [2, 4], [1, 0], [0, 3], [0, 0], [4, 2], [11, 5], [0, 9], [3, 4]], "devacc": 81.2, "acc": 80.13}, "17_head": {"device": ["2"], "batch_size": 1000, "kfold": 5, "usepytorch": true, "task_path": "./SentEval/data/", "cache_path": "./cache/", "result_path": "./ds_top_head_wise_results/", "optim": "rmsprop", "cbatch_size": 256, "tenacity": 3, "epoch_size": 2, "model_name": "bert-base-uncased", "task": "SICKEntailment", "num_head": 17, "intv_head": 1, "total_head": 40, "location": "head", "head_size": 64, "dropout": 0, "nhid": 0, "seed": 123, "classifier": {"nhid": 0, "optim": "rmsprop", "tenacity": 3, "epoch_size": 2, "dropout": 0, "batch_size": 256}, "heads": [[1, 9], [3, 2], [1, 8], [2, 2], [5, 3], [0, 4], [2, 7], [5, 8], [2, 4], [1, 0], [0, 3], [0, 0], [4, 2], [11, 5], [0, 9], [3, 4], [1, 10]], "devacc": 81.0, "acc": 80.17}, "19_head": {"device": ["2"], "batch_size": 1000, "kfold": 5, "usepytorch": true, "task_path": "./SentEval/data/", "cache_path": "./cache/", "result_path": "./ds_top_head_wise_results/", "optim": "rmsprop", "cbatch_size": 256, "tenacity": 3, "epoch_size": 2, "model_name": "bert-base-uncased", "task": "SICKEntailment", "num_head": 19, "intv_head": 1, "total_head": 40, "location": "head", "head_size": 64, "dropout": 0, "nhid": 0, "seed": 123, "classifier": {"nhid": 0, "optim": "rmsprop", "tenacity": 3, "epoch_size": 2, "dropout": 0, "batch_size": 256}, "heads": [[1, 9], [3, 2], [1, 8], [2, 2], [5, 3], [0, 4], [2, 7], [5, 8], [2, 4], [1, 0], [0, 3], [0, 0], [4, 2], [11, 5], [0, 9], [3, 4], [1, 10], [2, 8], [2, 10]], "devacc": 81.0, "acc": 80.39}, "20_head": {"device": ["2"], "batch_size": 1000, "kfold": 5, "usepytorch": true, "task_path": "./SentEval/data/", "cache_path": "./cache/", "result_path": "./ds_top_head_wise_results/", "optim": "rmsprop", "cbatch_size": 256, "tenacity": 3, "epoch_size": 2, "model_name": "bert-base-uncased", "task": "SICKEntailment", "num_head": 20, "intv_head": 1, "total_head": 40, "location": "head", "head_size": 64, "dropout": 0, "nhid": 0, "seed": 123, "classifier": {"nhid": 0, "optim": "rmsprop", "tenacity": 3, "epoch_size": 2, "dropout": 0, "batch_size": 256}, "heads": [[1, 9], [3, 2], [1, 8], [2, 2], [5, 3], [0, 4], [2, 7], [5, 8], [2, 4], [1, 0], [0, 3], [0, 0], [4, 2], [11, 5], [0, 9], [3, 4], [1, 10], [2, 8], [2, 10], [2, 6]], "devacc": 80.6, "acc": 80.25}, "22_head": {"device": ["2"], "batch_size": 1000, "kfold": 5, "usepytorch": true, "task_path": "./SentEval/data/", "cache_path": "./cache/", "result_path": "./ds_top_head_wise_results/", "optim": "rmsprop", "cbatch_size": 256, "tenacity": 3, "epoch_size": 2, "model_name": "bert-base-uncased", "task": "SICKEntailment", "num_head": 22, "intv_head": 1, "total_head": 40, "location": "head", "head_size": 64, "dropout": 0, "nhid": 0, "seed": 123, "classifier": {"nhid": 0, "optim": "rmsprop", "tenacity": 3, "epoch_size": 2, "dropout": 0, "batch_size": 256}, "heads": [[1, 9], [3, 2], [1, 8], [2, 2], [5, 3], [0, 4], [2, 7], [5, 8], [2, 4], [1, 0], [0, 3], [0, 0], [4, 2], [11, 5], [0, 9], [3, 4], [1, 10], [2, 8], [2, 10], [2, 6], [5, 4], [3, 8]], "devacc": 80.4, "acc": 80.11}, "23_head": {"device": ["2"], "batch_size": 1000, "kfold": 5, "usepytorch": true, "task_path": "./SentEval/data/", "cache_path": "./cache/", "result_path": "./ds_top_head_wise_results/", "optim": "rmsprop", "cbatch_size": 256, "tenacity": 3, "epoch_size": 2, "model_name": "bert-base-uncased", "task": "SICKEntailment", "num_head": 23, "intv_head": 1, "total_head": 40, "location": "head", "head_size": 64, "dropout": 0, "nhid": 0, "seed": 123, "classifier": {"nhid": 0, "optim": "rmsprop", "tenacity": 3, "epoch_size": 2, "dropout": 0, "batch_size": 256}, "heads": [[1, 9], [3, 2], [1, 8], [2, 2], [5, 3], [0, 4], [2, 7], [5, 8], [2, 4], [1, 0], [0, 3], [0, 0], [4, 2], [11, 5], [0, 9], [3, 4], [1, 10], [2, 8], [2, 10], [2, 6], [5, 4], [3, 8], [11, 11]], "devacc": 82.0, "acc": 79.93}, "25_head": {"device": ["2"], "batch_size": 1000, "kfold": 5, "usepytorch": true, "task_path": "./SentEval/data/", "cache_path": "./cache/", "result_path": "./ds_top_head_wise_results/", "optim": "rmsprop", "cbatch_size": 256, "tenacity": 3, "epoch_size": 2, "model_name": "bert-base-uncased", "task": "SICKEntailment", "num_head": 25, "intv_head": 1, "total_head": 40, "location": "head", "head_size": 64, "dropout": 0, "nhid": 0, "seed": 123, "classifier": {"nhid": 0, "optim": "rmsprop", "tenacity": 3, "epoch_size": 2, "dropout": 0, "batch_size": 256}, "heads": [[1, 9], [3, 2], [1, 8], [2, 2], [5, 3], [0, 4], [2, 7], [5, 8], [2, 4], [1, 0], [0, 3], [0, 0], [4, 2], [11, 5], [0, 9], [3, 4], [1, 10], [2, 8], [2, 10], [2, 6], [5, 4], [3, 8], [11, 11], [1, 5], [1, 11]], "devacc": 82.0, "acc": 80.15}, "26_head": {"device": ["2"], "batch_size": 1000, "kfold": 5, "usepytorch": true, "task_path": "./SentEval/data/", "cache_path": "./cache/", "result_path": "./ds_top_head_wise_results/", "optim": "rmsprop", "cbatch_size": 256, "tenacity": 3, "epoch_size": 2, "model_name": "bert-base-uncased", "task": "SICKEntailment", "num_head": 26, "intv_head": 1, "total_head": 40, "location": "head", "head_size": 64, "dropout": 0, "nhid": 0, "seed": 123, "classifier": {"nhid": 0, "optim": "rmsprop", "tenacity": 3, "epoch_size": 2, "dropout": 0, "batch_size": 256}, "heads": [[1, 9], [3, 2], [1, 8], [2, 2], [5, 3], [0, 4], [2, 7], [5, 8], [2, 4], [1, 0], [0, 3], [0, 0], [4, 2], [11, 5], [0, 9], [3, 4], [1, 10], [2, 8], [2, 10], [2, 6], [5, 4], [3, 8], [11, 11], [1, 5], [1, 11], [2, 1]], "devacc": 81.8, "acc": 80.43}, "28_head": {"device": ["2"], "batch_size": 1000, "kfold": 5, "usepytorch": true, "task_path": "./SentEval/data/", "cache_path": "./cache/", "result_path": "./ds_top_head_wise_results/", "optim": "rmsprop", "cbatch_size": 256, "tenacity": 3, "epoch_size": 2, "model_name": "bert-base-uncased", "task": "SICKEntailment", "num_head": 28, "intv_head": 1, "total_head": 40, "location": "head", "head_size": 64, "dropout": 0, "nhid": 0, "seed": 123, "classifier": {"nhid": 0, "optim": "rmsprop", "tenacity": 3, "epoch_size": 2, "dropout": 0, "batch_size": 256}, "heads": [[1, 9], [3, 2], [1, 8], [2, 2], [5, 3], [0, 4], [2, 7], [5, 8], [2, 4], [1, 0], [0, 3], [0, 0], [4, 2], [11, 5], [0, 9], [3, 4], [1, 10], [2, 8], [2, 10], [2, 6], [5, 4], [3, 8], [11, 11], [1, 5], [1, 11], [2, 1], [1, 3], [2, 3]], "devacc": 81.2, "acc": 79.72}, "29_head": {"device": ["2"], "batch_size": 1000, "kfold": 5, "usepytorch": true, "task_path": "./SentEval/data/", "cache_path": "./cache/", "result_path": "./ds_top_head_wise_results/", "optim": "rmsprop", "cbatch_size": 256, "tenacity": 3, "epoch_size": 2, "model_name": "bert-base-uncased", "task": "SICKEntailment", "num_head": 29, "intv_head": 1, "total_head": 40, "location": "head", "head_size": 64, "dropout": 0, "nhid": 0, "seed": 123, "classifier": {"nhid": 0, "optim": "rmsprop", "tenacity": 3, "epoch_size": 2, "dropout": 0, "batch_size": 256}, "heads": [[1, 9], [3, 2], [1, 8], [2, 2], [5, 3], [0, 4], [2, 7], [5, 8], [2, 4], [1, 0], [0, 3], [0, 0], [4, 2], [11, 5], [0, 9], [3, 4], [1, 10], [2, 8], [2, 10], [2, 6], [5, 4], [3, 8], [11, 11], [1, 5], [1, 11], [2, 1], [1, 3], [2, 3], [7, 1]], "devacc": 81.6, "acc": 79.46}, "31_head": {"device": ["2"], "batch_size": 1000, "kfold": 5, "usepytorch": true, "task_path": "./SentEval/data/", "cache_path": "./cache/", "result_path": "./ds_top_head_wise_results/", "optim": "rmsprop", "cbatch_size": 256, "tenacity": 3, "epoch_size": 2, "model_name": "bert-base-uncased", "task": "SICKEntailment", "num_head": 31, "intv_head": 1, "total_head": 40, "location": "head", "head_size": 64, "dropout": 0, "nhid": 0, "seed": 123, "classifier": {"nhid": 0, "optim": "rmsprop", "tenacity": 3, "epoch_size": 2, "dropout": 0, "batch_size": 256}, "heads": [[1, 9], [3, 2], [1, 8], [2, 2], [5, 3], [0, 4], [2, 7], [5, 8], [2, 4], [1, 0], [0, 3], [0, 0], [4, 2], [11, 5], [0, 9], [3, 4], [1, 10], [2, 8], [2, 10], [2, 6], [5, 4], [3, 8], [11, 11], [1, 5], [1, 11], [2, 1], [1, 3], [2, 3], [7, 1], [3, 7], [2, 5]], "devacc": 81.8, "acc": 78.89}, "32_head": {"device": ["2"], "batch_size": 1000, "kfold": 5, "usepytorch": true, "task_path": "./SentEval/data/", "cache_path": "./cache/", "result_path": "./ds_top_head_wise_results/", "optim": "rmsprop", "cbatch_size": 256, "tenacity": 3, "epoch_size": 2, "model_name": "bert-base-uncased", "task": "SICKEntailment", "num_head": 32, "intv_head": 1, "total_head": 40, "location": "head", "head_size": 64, "dropout": 0, "nhid": 0, "seed": 123, "classifier": {"nhid": 0, "optim": "rmsprop", "tenacity": 3, "epoch_size": 2, "dropout": 0, "batch_size": 256}, "heads": [[1, 9], [3, 2], [1, 8], [2, 2], [5, 3], [0, 4], [2, 7], [5, 8], [2, 4], [1, 0], [0, 3], [0, 0], [4, 2], [11, 5], [0, 9], [3, 4], [1, 10], [2, 8], [2, 10], [2, 6], [5, 4], [3, 8], [11, 11], [1, 5], [1, 11], [2, 1], [1, 3], [2, 3], [7, 1], [3, 7], [2, 5], [11, 9]], "devacc": 81.4, "acc": 79.28}, "34_head": {"device": ["2"], "batch_size": 1000, "kfold": 5, "usepytorch": true, "task_path": "./SentEval/data/", "cache_path": "./cache/", "result_path": "./ds_top_head_wise_results/", "optim": "rmsprop", "cbatch_size": 256, "tenacity": 3, "epoch_size": 2, "model_name": "bert-base-uncased", "task": "SICKEntailment", "num_head": 34, "intv_head": 1, "total_head": 40, "location": "head", "head_size": 64, "dropout": 0, "nhid": 0, "seed": 123, "classifier": {"nhid": 0, "optim": "rmsprop", "tenacity": 3, "epoch_size": 2, "dropout": 0, "batch_size": 256}, "heads": [[1, 9], [3, 2], [1, 8], [2, 2], [5, 3], [0, 4], [2, 7], [5, 8], [2, 4], [1, 0], [0, 3], [0, 0], [4, 2], [11, 5], [0, 9], [3, 4], [1, 10], [2, 8], [2, 10], [2, 6], [5, 4], [3, 8], [11, 11], [1, 5], [1, 11], [2, 1], [1, 3], [2, 3], [7, 1], [3, 7], [2, 5], [11, 9], [4, 9], [8, 7]], "devacc": 80.2, "acc": 79.42}, "35_head": {"device": ["2"], "batch_size": 1000, "kfold": 5, "usepytorch": true, "task_path": "./SentEval/data/", "cache_path": "./cache/", "result_path": "./ds_top_head_wise_results/", "optim": "rmsprop", "cbatch_size": 256, "tenacity": 3, "epoch_size": 2, "model_name": "bert-base-uncased", "task": "SICKEntailment", "num_head": 35, "intv_head": 1, "total_head": 40, "location": "head", "head_size": 64, "dropout": 0, "nhid": 0, "seed": 123, "classifier": {"nhid": 0, "optim": "rmsprop", "tenacity": 3, "epoch_size": 2, "dropout": 0, "batch_size": 256}, "heads": [[1, 9], [3, 2], [1, 8], [2, 2], [5, 3], [0, 4], [2, 7], [5, 8], [2, 4], [1, 0], [0, 3], [0, 0], [4, 2], [11, 5], [0, 9], [3, 4], [1, 10], [2, 8], [2, 10], [2, 6], [5, 4], [3, 8], [11, 11], [1, 5], [1, 11], [2, 1], [1, 3], [2, 3], [7, 1], [3, 7], [2, 5], [11, 9], [4, 9], [8, 7], [10, 3]], "devacc": 80.2, "acc": 79.81}, "37_head": {"device": ["2"], "batch_size": 1000, "kfold": 5, "usepytorch": true, "task_path": "./SentEval/data/", "cache_path": "./cache/", "result_path": "./ds_top_head_wise_results/", "optim": "rmsprop", "cbatch_size": 256, "tenacity": 3, "epoch_size": 2, "model_name": "bert-base-uncased", "task": "SICKEntailment", "num_head": 37, "intv_head": 1, "total_head": 40, "location": "head", "head_size": 64, "dropout": 0, "nhid": 0, "seed": 123, "classifier": {"nhid": 0, "optim": "rmsprop", "tenacity": 3, "epoch_size": 2, "dropout": 0, "batch_size": 256}, "heads": [[1, 9], [3, 2], [1, 8], [2, 2], [5, 3], [0, 4], [2, 7], [5, 8], [2, 4], [1, 0], [0, 3], [0, 0], [4, 2], [11, 5], [0, 9], [3, 4], [1, 10], [2, 8], [2, 10], [2, 6], [5, 4], [3, 8], [11, 11], [1, 5], [1, 11], [2, 1], [1, 3], [2, 3], [7, 1], [3, 7], [2, 5], [11, 9], [4, 9], [8, 7], [10, 3], [9, 10], [6, 5]], "devacc": 81.8, "acc": 80.23}, "38_head": {"device": ["2"], "batch_size": 1000, "kfold": 5, "usepytorch": true, "task_path": "./SentEval/data/", "cache_path": "./cache/", "result_path": "./ds_top_head_wise_results/", "optim": "rmsprop", "cbatch_size": 256, "tenacity": 3, "epoch_size": 2, "model_name": "bert-base-uncased", "task": "SICKEntailment", "num_head": 38, "intv_head": 1, "total_head": 40, "location": "head", "head_size": 64, "dropout": 0, "nhid": 0, "seed": 123, "classifier": {"nhid": 0, "optim": "rmsprop", "tenacity": 3, "epoch_size": 2, "dropout": 0, "batch_size": 256}, "heads": [[1, 9], [3, 2], [1, 8], [2, 2], [5, 3], [0, 4], [2, 7], [5, 8], [2, 4], [1, 0], [0, 3], [0, 0], [4, 2], [11, 5], [0, 9], [3, 4], [1, 10], [2, 8], [2, 10], [2, 6], [5, 4], [3, 8], [11, 11], [1, 5], [1, 11], [2, 1], [1, 3], [2, 3], [7, 1], [3, 7], [2, 5], [11, 9], [4, 9], [8, 7], [10, 3], [9, 10], [6, 5], [11, 8]], "devacc": 81.4, "acc": 80.41}, "40_head": {"device": ["2"], "batch_size": 1000, "kfold": 5, "usepytorch": true, "task_path": "./SentEval/data/", "cache_path": "./cache/", "result_path": "./ds_top_head_wise_results/", "optim": "rmsprop", "cbatch_size": 256, "tenacity": 3, "epoch_size": 2, "model_name": "bert-base-uncased", "task": "SICKEntailment", "num_head": 40, "intv_head": 1, "total_head": 40, "location": "head", "head_size": 64, "dropout": 0, "nhid": 0, "seed": 123, "classifier": {"nhid": 0, "optim": "rmsprop", "tenacity": 3, "epoch_size": 2, "dropout": 0, "batch_size": 256}, "heads": [[1, 9], [3, 2], [1, 8], [2, 2], [5, 3], [0, 4], [2, 7], [5, 8], [2, 4], [1, 0], [0, 3], [0, 0], [4, 2], [11, 5], [0, 9], [3, 4], [1, 10], [2, 8], [2, 10], [2, 6], [5, 4], [3, 8], [11, 11], [1, 5], [1, 11], [2, 1], [1, 3], [2, 3], [7, 1], [3, 7], [2, 5], [11, 9], [4, 9], [8, 7], [10, 3], [9, 10], [6, 5], [11, 8], [1, 4], [11, 6]], "devacc": 81.4, "acc": 80.09}}